clock_generator.v
module clock_generator (

input clk,
input reset,
input manual_clk,
input clk_select,
output sel_out,
output slow_out
);

reg [7:0] counter;
reg slow_clk;

assign sel_out = (clk_select) ? manual_clk : slow_clk;
assign slow_out = slow_clk;

// counter size calculation according to input and output frequencies
parameter incoming_clk = 50000000;  // 50 MHz system clock
parameter slow = 5000000;  // 1 MHz clock output
parameter half_div = incoming_clk / (2*slow); // max-counter size

initial begin
	counter = 0;
	slow_clk = 0;
end

always@(negedge clk) begin
	if (reset) begin
		counter <= 0;
		slow_clk <= 0;
	end else begin
	  if (counter == half_div - 1)
	    begin
	    counter <= 0;
	    slow_clk <= ~slow_clk;
	    end
	  else
	    begin
	    counter <= counter + 1'd1;
	    end
	  end
	end
endmodule

clock_gen_tb.v
module clock_gen_tb;
  reg clk, reset;

reg manual, sel, slow;

clock_generator U0 (
  .clk	(clk),
	.manual_clk		(manual),
	.clk_select			(sel)
);

  initial begin
    clk = 0;
		sel = 0;
		manual = 0;
  end

  always
    #5 clk = !clk;


  initial  begin
    $dumpfile ("clk_gen.vcd");
    $dumpvars;
  end

  initial  begin
    $display("\t\ttime,\tclk,\ticycle");
    $monitor("%d,\t%b,\t%b",$time, clk,reset);
  end

  initial
  #5000 $finish;

  //Rest of testbench code after this line

endmodule

clk_gen.vcd
$date
	Mon Mar 20 16:36:22 2017
$end
$version
	Icarus Verilog
$end
$timescale
	1s
$end
$scope module clock_gen_tb $end
$var reg 1 ! clk $end
$var reg 1 " manual $end
$var reg 1 # reset $end
$var reg 1 $ sel $end
$scope module U0 $end
$var wire 1 ! clk $end
$var wire 1 $ clk_select $end
$var wire 1 " manual_clk $end
$var wire 1 % reset $end
$var wire 1 & slow_out $end
$var wire 1 ' sel_out $end
$var reg 8 ( counter [7:0] $end
$var reg 1 ) slow_clk $end
$upscope $end
$upscope $end
$enddefinitions $end
#0
$dumpvars
0)
b1 (
0'
0&
z%
0$
x#
0"
0!
$end
#5
1!
#10
b10 (
0!
#15
1!
#20
b11 (
0!
#25
1!
#30
b100 (
0!
#35
1!
#40
1'
1&
1)
b0 (
0!
#45
1!
#50
b1 (
0!
#55
1!
#60
b10 (
0!
#65
1!
#70
b11 (
0!
#75
1!
#80
b100 (
0!
#85
1!
#90
0'
0&
0)
b0 (
0!
#95
1!
#100
b1 (
0!
#105
1!
#110
b10 (
0!
#115
1!
#120
b11 (
0!
#125
1!
#130
b100 (
0!
#135
1!
#140
1'
1&
1)
b0 (
0!
#145
1!
#150
b1 (
0!
#155
1!
#160
b10 (
0!
#165
1!
#170
b11 (
0!
#175
1!
#180
b100 (
0!
#185
1!
#190
0'
0&
0)
b0 (
0!
#195
1!
#200
b1 (
0!
#205
1!
#210
b10 (
0!
#215
1!
#220
b11 (
0!
#225
1!
#230
b100 (
0!
#235
1!
#240
1'
1&
1)
b0 (
0!
#245
1!
#250
b1 (
0!
#255
1!
#260
b10 (
0!
#265
1!
#270
b11 (
0!
#275
1!
#280
b100 (
0!
#285
1!
#290
0'
0&
0)
b0 (
0!
#295
1!
#300
b1 (
0!
#305
1!
#310
b10 (
0!
#315
1!
#320
b11 (
0!
#325
1!
#330
b100 (
0!
#335
1!
#340
1'
1&
1)
b0 (
0!
#345
1!
#350
b1 (
0!
#355
1!
#360
b10 (
0!
#365
1!
#370
b11 (
0!
#375
1!
#380
b100 (
0!
#385
1!
#390
0'
0&
0)
b0 (
0!
#395
1!
#400
b1 (
0!
#405
1!
#410
b10 (
0!
#415
1!
#420
b11 (
0!
#425
1!
#430
b100 (
0!
#435
1!
#440
1'
1&
1)
b0 (
0!
#445
1!
#450
b1 (
0!
#455
1!
#460
b10 (
0!
#465
1!
#470
b11 (
0!
#475
1!
#480
b100 (
0!
#485
1!
#490
0'
0&
0)
b0 (
0!
#495
1!
#500
b1 (
0!
#505
1!
#510
b10 (
0!
#515
1!
#520
b11 (
0!
#525
1!
#530
b100 (
0!
#535
1!
#540
1'
1&
1)
b0 (
0!
#545
1!
#550
b1 (
0!
#555
1!
#560
b10 (
0!
#565
1!
#570
b11 (
0!
#575
1!
#580
b100 (
0!
#585
1!
#590
0'
0&
0)
b0 (
0!
#595
1!
#600
b1 (
0!
#605
1!
#610
b10 (
0!
#615
1!
#620
b11 (
0!
#625
1!
#630
b100 (
0!
#635
1!
#640
1'
1&
1)
b0 (
0!
#645
1!
#650
b1 (
0!
#655
1!
#660
b10 (
0!
#665
1!
#670
b11 (
0!
#675
1!
#680
b100 (
0!
#685
1!
#690
0'
0&
0)
b0 (
0!
#695
1!
#700
b1 (
0!
#705
1!
#710
b10 (
0!
#715
1!
#720
b11 (
0!
#725
1!
#730
b100 (
0!
#735
1!
#740
1'
1&
1)
b0 (
0!
#745
1!
#750
b1 (
0!
#755
1!
#760
b10 (
0!
#765
1!
#770
b11 (
0!
#775
1!
#780
b100 (
0!
#785
1!
#790
0'
0&
0)
b0 (
0!
#795
1!
#800
b1 (
0!
#805
1!
#810
b10 (
0!
#815
1!
#820
b11 (
0!
#825
1!
#830
b100 (
0!
#835
1!
#840
1'
1&
1)
b0 (
0!
#845
1!
#850
b1 (
0!
#855
1!
#860
b10 (
0!
#865
1!
#870
b11 (
0!
#875
1!
#880
b100 (
0!
#885
1!
#890
0'
0&
0)
b0 (
0!
#895
1!
#900
b1 (
0!
#905
1!
#910
b10 (
0!
#915
1!
#920
b11 (
0!
#925
1!
#930
b100 (
0!
#935
1!
#940
1'
1&
1)
b0 (
0!
#945
1!
#950
b1 (
0!
#955
1!
#960
b10 (
0!
#965
1!
#970
b11 (
0!
#975
1!
#980
b100 (
0!
#985
1!
#990
0'
0&
0)
b0 (
0!
#995
1!
#1000
b1 (
0!
#1005
1!
#1010
b10 (
0!
#1015
1!
#1020
b11 (
0!
#1025
1!
#1030
b100 (
0!
#1035
1!
#1040
1'
1&
1)
b0 (
0!
#1045
1!
#1050
b1 (
0!
#1055
1!
#1060
b10 (
0!
#1065
1!
#1070
b11 (
0!
#1075
1!
#1080
b100 (
0!
#1085
1!
#1090
0'
0&
0)
b0 (
0!
#1095
1!
#1100
b1 (
0!
#1105
1!
#1110
b10 (
0!
#1115
1!
#1120
b11 (
0!
#1125
1!
#1130
b100 (
0!
#1135
1!
#1140
1'
1&
1)
b0 (
0!
#1145
1!
#1150
b1 (
0!
#1155
1!
#1160
b10 (
0!
#1165
1!
#1170
b11 (
0!
#1175
1!
#1180
b100 (
0!
#1185
1!
#1190
0'
0&
0)
b0 (
0!
#1195
1!
#1200
b1 (
0!
#1205
1!
#1210
b10 (
0!
#1215
1!
#1220
b11 (
0!
#1225
1!
#1230
b100 (
0!
#1235
1!
#1240
1'
1&
1)
b0 (
0!
#1245
1!
#1250
b1 (
0!
#1255
1!
#1260
b10 (
0!
#1265
1!
#1270
b11 (
0!
#1275
1!
#1280
b100 (
0!
#1285
1!
#1290
0'
0&
0)
b0 (
0!
#1295
1!
#1300
b1 (
0!
#1305
1!
#1310
b10 (
0!
#1315
1!
#1320
b11 (
0!
#1325
1!
#1330
b100 (
0!
#1335
1!
#1340
1'
1&
1)
b0 (
0!
#1345
1!
#1350
b1 (
0!
#1355
1!
#1360
b10 (
0!
#1365
1!
#1370
b11 (
0!
#1375
1!
#1380
b100 (
0!
#1385
1!
#1390
0'
0&
0)
b0 (
0!
#1395
1!
#1400
b1 (
0!
#1405
1!
#1410
b10 (
0!
#1415
1!
#1420
b11 (
0!
#1425
1!
#1430
b100 (
0!
#1435
1!
#1440
1'
1&
1)
b0 (
0!
#1445
1!
#1450
b1 (
0!
#1455
1!
#1460
b10 (
0!
#1465
1!
#1470
b11 (
0!
#1475
1!
#1480
b100 (
0!
#1485
1!
#1490
0'
0&
0)
b0 (
0!
#1495
1!
#1500
b1 (
0!
#1505
1!
#1510
b10 (
0!
#1515
1!
#1520
b11 (
0!
#1525
1!
#1530
b100 (
0!
#1535
1!
#1540
1'
1&
1)
b0 (
0!
#1545
1!
#1550
b1 (
0!
#1555
1!
#1560
b10 (
0!
#1565
1!
#1570
b11 (
0!
#1575
1!
#1580
b100 (
0!
#1585
1!
#1590
0'
0&
0)
b0 (
0!
#1595
1!
#1600
b1 (
0!
#1605
1!
#1610
b10 (
0!
#1615
1!
#1620
b11 (
0!
#1625
1!
#1630
b100 (
0!
#1635
1!
#1640
1'
1&
1)
b0 (
0!
#1645
1!
#1650
b1 (
0!
#1655
1!
#1660
b10 (
0!
#1665
1!
#1670
b11 (
0!
#1675
1!
#1680
b100 (
0!
#1685
1!
#1690
0'
0&
0)
b0 (
0!
#1695
1!
#1700
b1 (
0!
#1705
1!
#1710
b10 (
0!
#1715
1!
#1720
b11 (
0!
#1725
1!
#1730
b100 (
0!
#1735
1!
#1740
1'
1&
1)
b0 (
0!
#1745
1!
#1750
b1 (
0!
#1755
1!
#1760
b10 (
0!
#1765
1!
#1770
b11 (
0!
#1775
1!
#1780
b100 (
0!
#1785
1!
#1790
0'
0&
0)
b0 (
0!
#1795
1!
#1800
b1 (
0!
#1805
1!
#1810
b10 (
0!
#1815
1!
#1820
b11 (
0!
#1825
1!
#1830
b100 (
0!
#1835
1!
#1840
1'
1&
1)
b0 (
0!
#1845
1!
#1850
b1 (
0!
#1855
1!
#1860
b10 (
0!
#1865
1!
#1870
b11 (
0!
#1875
1!
#1880
b100 (
0!
#1885
1!
#1890
0'
0&
0)
b0 (
0!
#1895
1!
#1900
b1 (
0!
#1905
1!
#1910
b10 (
0!
#1915
1!
#1920
b11 (
0!
#1925
1!
#1930
b100 (
0!
#1935
1!
#1940
1'
1&
1)
b0 (
0!
#1945
1!
#1950
b1 (
0!
#1955
1!
#1960
b10 (
0!
#1965
1!
#1970
b11 (
0!
#1975
1!
#1980
b100 (
0!
#1985
1!
#1990
0'
0&
0)
b0 (
0!
#1995
1!
#2000
b1 (
0!
#2005
1!
#2010
b10 (
0!
#2015
1!
#2020
b11 (
0!
#2025
1!
#2030
b100 (
0!
#2035
1!
#2040
1'
1&
1)
b0 (
0!
#2045
1!
#2050
b1 (
0!
#2055
1!
#2060
b10 (
0!
#2065
1!
#2070
b11 (
0!
#2075
1!
#2080
b100 (
0!
#2085
1!
#2090
0'
0&
0)
b0 (
0!
#2095
1!
#2100
b1 (
0!
#2105
1!
#2110
b10 (
0!
#2115
1!
#2120
b11 (
0!
#2125
1!
#2130
b100 (
0!
#2135
1!
#2140
1'
1&
1)
b0 (
0!
#2145
1!
#2150
b1 (
0!
#2155
1!
#2160
b10 (
0!
#2165
1!
#2170
b11 (
0!
#2175
1!
#2180
b100 (
0!
#2185
1!
#2190
0'
0&
0)
b0 (
0!
#2195
1!
#2200
b1 (
0!
#2205
1!
#2210
b10 (
0!
#2215
1!
#2220
b11 (
0!
#2225
1!
#2230
b100 (
0!
#2235
1!
#2240
1'
1&
1)
b0 (
0!
#2245
1!
#2250
b1 (
0!
#2255
1!
#2260
b10 (
0!
#2265
1!
#2270
b11 (
0!
#2275
1!
#2280
b100 (
0!
#2285
1!
#2290
0'
0&
0)
b0 (
0!
#2295
1!
#2300
b1 (
0!
#2305
1!
#2310
b10 (
0!
#2315
1!
#2320
b11 (
0!
#2325
1!
#2330
b100 (
0!
#2335
1!
#2340
1'
1&
1)
b0 (
0!
#2345
1!
#2350
b1 (
0!
#2355
1!
#2360
b10 (
0!
#2365
1!
#2370
b11 (
0!
#2375
1!
#2380
b100 (
0!
#2385
1!
#2390
0'
0&
0)
b0 (
0!
#2395
1!
#2400
b1 (
0!
#2405
1!
#2410
b10 (
0!
#2415
1!
#2420
b11 (
0!
#2425
1!
#2430
b100 (
0!
#2435
1!
#2440
1'
1&
1)
b0 (
0!
#2445
1!
#2450
b1 (
0!
#2455
1!
#2460
b10 (
0!
#2465
1!
#2470
b11 (
0!
#2475
1!
#2480
b100 (
0!
#2485
1!
#2490
0'
0&
0)
b0 (
0!
#2495
1!
#2500
b1 (
0!
#2505
1!
#2510
b10 (
0!
#2515
1!
#2520
b11 (
0!
#2525
1!
#2530
b100 (
0!
#2535
1!
#2540
1'
1&
1)
b0 (
0!
#2545
1!
#2550
b1 (
0!
#2555
1!
#2560
b10 (
0!
#2565
1!
#2570
b11 (
0!
#2575
1!
#2580
b100 (
0!
#2585
1!
#2590
0'
0&
0)
b0 (
0!
#2595
1!
#2600
b1 (
0!
#2605
1!
#2610
b10 (
0!
#2615
1!
#2620
b11 (
0!
#2625
1!
#2630
b100 (
0!
#2635
1!
#2640
1'
1&
1)
b0 (
0!
#2645
1!
#2650
b1 (
0!
#2655
1!
#2660
b10 (
0!
#2665
1!
#2670
b11 (
0!
#2675
1!
#2680
b100 (
0!
#2685
1!
#2690
0'
0&
0)
b0 (
0!
#2695
1!
#2700
b1 (
0!
#2705
1!
#2710
b10 (
0!
#2715
1!
#2720
b11 (
0!
#2725
1!
#2730
b100 (
0!
#2735
1!
#2740
1'
1&
1)
b0 (
0!
#2745
1!
#2750
b1 (
0!
#2755
1!
#2760
b10 (
0!
#2765
1!
#2770
b11 (
0!
#2775
1!
#2780
b100 (
0!
#2785
1!
#2790
0'
0&
0)
b0 (
0!
#2795
1!
#2800
b1 (
0!
#2805
1!
#2810
b10 (
0!
#2815
1!
#2820
b11 (
0!
#2825
1!
#2830
b100 (
0!
#2835
1!
#2840
1'
1&
1)
b0 (
0!
#2845
1!
#2850
b1 (
0!
#2855
1!
#2860
b10 (
0!
#2865
1!
#2870
b11 (
0!
#2875
1!
#2880
b100 (
0!
#2885
1!
#2890
0'
0&
0)
b0 (
0!
#2895
1!
#2900
b1 (
0!
#2905
1!
#2910
b10 (
0!
#2915
1!
#2920
b11 (
0!
#2925
1!
#2930
b100 (
0!
#2935
1!
#2940
1'
1&
1)
b0 (
0!
#2945
1!
#2950
b1 (
0!
#2955
1!
#2960
b10 (
0!
#2965
1!
#2970
b11 (
0!
#2975
1!
#2980
b100 (
0!
#2985
1!
#2990
0'
0&
0)
b0 (
0!
#2995
1!
#3000
b1 (
0!
#3005
1!
#3010
b10 (
0!
#3015
1!
#3020
b11 (
0!
#3025
1!
#3030
b100 (
0!
#3035
1!
#3040
1'
1&
1)
b0 (
0!
#3045
1!
#3050
b1 (
0!
#3055
1!
#3060
b10 (
0!
#3065
1!
#3070
b11 (
0!
#3075
1!
#3080
b100 (
0!
#3085
1!
#3090
0'
0&
0)
b0 (
0!
#3095
1!
#3100
b1 (
0!
#3105
1!
#3110
b10 (
0!
#3115
1!
#3120
b11 (
0!
#3125
1!
#3130
b100 (
0!
#3135
1!
#3140
1'
1&
1)
b0 (
0!
#3145
1!
#3150
b1 (
0!
#3155
1!
#3160
b10 (
0!
#3165
1!
#3170
b11 (
0!
#3175
1!
#3180
b100 (
0!
#3185
1!
#3190
0'
0&
0)
b0 (
0!
#3195
1!
#3200
b1 (
0!
#3205
1!
#3210
b10 (
0!
#3215
1!
#3220
b11 (
0!
#3225
1!
#3230
b100 (
0!
#3235
1!
#3240
1'
1&
1)
b0 (
0!
#3245
1!
#3250
b1 (
0!
#3255
1!
#3260
b10 (
0!
#3265
1!
#3270
b11 (
0!
#3275
1!
#3280
b100 (
0!
#3285
1!
#3290
0'
0&
0)
b0 (
0!
#3295
1!
#3300
b1 (
0!
#3305
1!
#3310
b10 (
0!
#3315
1!
#3320
b11 (
0!
#3325
1!
#3330
b100 (
0!
#3335
1!
#3340
1'
1&
1)
b0 (
0!
#3345
1!
#3350
b1 (
0!
#3355
1!
#3360
b10 (
0!
#3365
1!
#3370
b11 (
0!
#3375
1!
#3380
b100 (
0!
#3385
1!
#3390
0'
0&
0)
b0 (
0!
#3395
1!
#3400
b1 (
0!
#3405
1!
#3410
b10 (
0!
#3415
1!
#3420
b11 (
0!
#3425
1!
#3430
b100 (
0!
#3435
1!
#3440
1'
1&
1)
b0 (
0!
#3445
1!
#3450
b1 (
0!
#3455
1!
#3460
b10 (
0!
#3465
1!
#3470
b11 (
0!
#3475
1!
#3480
b100 (
0!
#3485
1!
#3490
0'
0&
0)
b0 (
0!
#3495
1!
#3500
b1 (
0!
#3505
1!
#3510
b10 (
0!
#3515
1!
#3520
b11 (
0!
#3525
1!
#3530
b100 (
0!
#3535
1!
#3540
1'
1&
1)
b0 (
0!
#3545
1!
#3550
b1 (
0!
#3555
1!
#3560
b10 (
0!
#3565
1!
#3570
b11 (
0!
#3575
1!
#3580
b100 (
0!
#3585
1!
#3590
0'
0&
0)
b0 (
0!
#3595
1!
#3600
b1 (
0!
#3605
1!
#3610
b10 (
0!
#3615
1!
#3620
b11 (
0!
#3625
1!
#3630
b100 (
0!
#3635
1!
#3640
1'
1&
1)
b0 (
0!
#3645
1!
#3650
b1 (
0!
#3655
1!
#3660
b10 (
0!
#3665
1!
#3670
b11 (
0!
#3675
1!
#3680
b100 (
0!
#3685
1!
#3690
0'
0&
0)
b0 (
0!
#3695
1!
#3700
b1 (
0!
#3705
1!
#3710
b10 (
0!
#3715
1!
#3720
b11 (
0!
#3725
1!
#3730
b100 (
0!
#3735
1!
#3740
1'
1&
1)
b0 (
0!
#3745
1!
#3750
b1 (
0!
#3755
1!
#3760
b10 (
0!
#3765
1!
#3770
b11 (
0!
#3775
1!
#3780
b100 (
0!
#3785
1!
#3790
0'
0&
0)
b0 (
0!
#3795
1!
#3800
b1 (
0!
#3805
1!
#3810
b10 (
0!
#3815
1!
#3820
b11 (
0!
#3825
1!
#3830
b100 (
0!
#3835
1!
#3840
1'
1&
1)
b0 (
0!
#3845
1!
#3850
b1 (
0!
#3855
1!
#3860
b10 (
0!
#3865
1!
#3870
b11 (
0!
#3875
1!
#3880
b100 (
0!
#3885
1!
#3890
0'
0&
0)
b0 (
0!
#3895
1!
#3900
b1 (
0!
#3905
1!
#3910
b10 (
0!
#3915
1!
#3920
b11 (
0!
#3925
1!
#3930
b100 (
0!
#3935
1!
#3940
1'
1&
1)
b0 (
0!
#3945
1!
#3950
b1 (
0!
#3955
1!
#3960
b10 (
0!
#3965
1!
#3970
b11 (
0!
#3975
1!
#3980
b100 (
0!
#3985
1!
#3990
0'
0&
0)
b0 (
0!
#3995
1!
#4000
b1 (
0!
#4005
1!
#4010
b10 (
0!
#4015
1!
#4020
b11 (
0!
#4025
1!
#4030
b100 (
0!
#4035
1!
#4040
1'
1&
1)
b0 (
0!
#4045
1!
#4050
b1 (
0!
#4055
1!
#4060
b10 (
0!
#4065
1!
#4070
b11 (
0!
#4075
1!
#4080
b100 (
0!
#4085
1!
#4090
0'
0&
0)
b0 (
0!
#4095
1!
#4100
b1 (
0!
#4105
1!
#4110
b10 (
0!
#4115
1!
#4120
b11 (
0!
#4125
1!
#4130
b100 (
0!
#4135
1!
#4140
1'
1&
1)
b0 (
0!
#4145
1!
#4150
b1 (
0!
#4155
1!
#4160
b10 (
0!
#4165
1!
#4170
b11 (
0!
#4175
1!
#4180
b100 (
0!
#4185
1!
#4190
0'
0&
0)
b0 (
0!
#4195
1!
#4200
b1 (
0!
#4205
1!
#4210
b10 (
0!
#4215
1!
#4220
b11 (
0!
#4225
1!
#4230
b100 (
0!
#4235
1!
#4240
1'
1&
1)
b0 (
0!
#4245
1!
#4250
b1 (
0!
#4255
1!
#4260
b10 (
0!
#4265
1!
#4270
b11 (
0!
#4275
1!
#4280
b100 (
0!
#4285
1!
#4290
0'
0&
0)
b0 (
0!
#4295
1!
#4300
b1 (
0!
#4305
1!
#4310
b10 (
0!
#4315
1!
#4320
b11 (
0!
#4325
1!
#4330
b100 (
0!
#4335
1!
#4340
1'
1&
1)
b0 (
0!
#4345
1!
#4350
b1 (
0!
#4355
1!
#4360
b10 (
0!
#4365
1!
#4370
b11 (
0!
#4375
1!
#4380
b100 (
0!
#4385
1!
#4390
0'
0&
0)
b0 (
0!
#4395
1!
#4400
b1 (
0!
#4405
1!
#4410
b10 (
0!
#4415
1!
#4420
b11 (
0!
#4425
1!
#4430
b100 (
0!
#4435
1!
#4440
1'
1&
1)
b0 (
0!
#4445
1!
#4450
b1 (
0!
#4455
1!
#4460
b10 (
0!
#4465
1!
#4470
b11 (
0!
#4475
1!
#4480
b100 (
0!
#4485
1!
#4490
0'
0&
0)
b0 (
0!
#4495
1!
#4500
b1 (
0!
#4505
1!
#4510
b10 (
0!
#4515
1!
#4520
b11 (
0!
#4525
1!
#4530
b100 (
0!
#4535
1!
#4540
1'
1&
1)
b0 (
0!
#4545
1!
#4550
b1 (
0!
#4555
1!
#4560
b10 (
0!
#4565
1!
#4570
b11 (
0!
#4575
1!
#4580
b100 (
0!
#4585
1!
#4590
0'
0&
0)
b0 (
0!
#4595
1!
#4600
b1 (
0!
#4605
1!
#4610
b10 (
0!
#4615
1!
#4620
b11 (
0!
#4625
1!
#4630
b100 (
0!
#4635
1!
#4640
1'
1&
1)
b0 (
0!
#4645
1!
#4650
b1 (
0!
#4655
1!
#4660
b10 (
0!
#4665
1!
#4670
b11 (
0!
#4675
1!
#4680
b100 (
0!
#4685
1!
#4690
0'
0&
0)
b0 (
0!
#4695
1!
#4700
b1 (
0!
#4705
1!
#4710
b10 (
0!
#4715
1!
#4720
b11 (
0!
#4725
1!
#4730
b100 (
0!
#4735
1!
#4740
1'
1&
1)
b0 (
0!
#4745
1!
#4750
b1 (
0!
#4755
1!
#4760
b10 (
0!
#4765
1!
#4770
b11 (
0!
#4775
1!
#4780
b100 (
0!
#4785
1!
#4790
0'
0&
0)
b0 (
0!
#4795
1!
#4800
b1 (
0!
#4805
1!
#4810
b10 (
0!
#4815
1!
#4820
b11 (
0!
#4825
1!
#4830
b100 (
0!
#4835
1!
#4840
1'
1&
1)
b0 (
0!
#4845
1!
#4850
b1 (
0!
#4855
1!
#4860
b10 (
0!
#4865
1!
#4870
b11 (
0!
#4875
1!
#4880
b100 (
0!
#4885
1!
#4890
0'
0&
0)
b0 (
0!
#4895
1!
#4900
b1 (
0!
#4905
1!
#4910
b10 (
0!
#4915
1!
#4920
b11 (
0!
#4925
1!
#4930
b100 (
0!
#4935
1!
#4940
1'
1&
1)
b0 (
0!
#4945
1!
#4950
b1 (
0!
#4955
1!
#4960
b10 (
0!
#4965
1!
#4970
b11 (
0!
#4975
1!
#4980
b100 (
0!
#4985
1!
#4990
0'
0&
0)
b0 (
0!
#4995
1!
#5000
b1 (
0!
