ram.v
module ram(
    output [15:0] data_out,
    input [15:0] address,
    input [15:0] data_in,
    input we,
    input clk
);
    reg [7:0] memory [0:255]; // byte addressable


    initial begin
      $readmemh("bios.hex", memory,0,3);
    end

    always @(negedge clk) begin
        if (we) begin
            memory[address] <= data_in[15:8];
            memory[address+1] <= data_in[7:0];
        end
    end

    assign data_out[15:8] = memory[address];
    assign data_out[7:0] = memory[address+1];

endmodule

ALU.v
module alu(
  x,y,
  f,
  out
);

  input       [15:0]  x,y;
  input       [2:0]   f;
  output      [15:0]  out;

  reg [15:0] out;


  always @* begin

    case(f)
      3'b000: out = x + y;
      3'b001: out = x - y;
			3'b010: out = x & y;
			3'b011: out = x | y;
			3'b110: out = (x << 9) | (y & 16'h1ff);
      default: out = x + y;
    endcase
  end

endmodule

regfile.v
// Regfile proof of concept
//

module regfile (
regr0,
regr1,
regw,
regr0s,
regr1s,
regws,
we,
incr_pc,
clk
);

input [15:0] regw;
input [2:0] regr0s, regr1s, regws;
input we, clk, incr_pc;
output [15:0] regr0, regr1;

reg [15:0] regr0, regr1;

reg [15:0] R1;
reg [15:0] R2;
reg [15:0] R3;
reg [15:0] R4;
reg [15:0] R5;
reg [15:0] R6;
reg [15:0] R7 = 0;

always @*
begin
	case(regr0s)
	3'b000: regr0 = 0;
	3'b001: regr0 = R1;
	3'b010: regr0 = R2;
	3'b011: regr0 = R3;
	3'b100: regr0 = R4;
	3'b101: regr0 = R5;
	3'b110: regr0 = R6;
	3'b111: regr0 = R7;
  default: regr0 = 0;
	endcase

	case(regr1s)
	3'b000: regr1 = 0;
	3'b001: regr1 = R1;
	3'b010: regr1 = R2;
	3'b011: regr1 = R3;
	3'b100: regr1 = R4;
	3'b101: regr1 = R5;
	3'b110: regr1 = R6;
	3'b111: regr1 = R7;
  default: regr0 = 0;
	endcase
end

always @(negedge clk)
begin
	if (we) begin
		case(regws)
		3'b001: R1 <= regw;
		3'b010: R2 <= regw;
		3'b011: R3 <= regw;
		3'b100: R4 <= regw;
		3'b101: R5 <= regw;
		3'b110: R6 <= regw;
		3'b111: R7 <= regw;
		endcase
	end

	// PC should auto increment always (?)
	if (incr_pc) begin
    R7 <= R7 + 2;
  end

end
endmodule

register_posedge.v
module register_posedge(
in, reset, load, clk, out
);

input [15:0] in;
input load, reset, clk;
output [15:0] out;

reg [15:0] out;

always @(posedge clk)
begin

if (reset && load)
	out <= 0;
else if (reset)
	out <= 0;
else if (load)
	out <= in;
end

endmodule

register.v
module register(
in, reset, load, clk, out
);

input [15:0] in;
input load, reset, clk;
output [15:0] out;

reg [15:0] out;

always @(negedge clk)
begin

if (reset && load)
	out <= 0;
else if (reset)
	out <= 0;
else if (load)
	out <= in;
end

endmodule

decoder.v
// decoder - proof of concept
//

module decoder (
  instr,
  MAR_LOAD,
  IR_LOAD,
  MDR_LOAD,
  REG_LOAD,
  RAM_LOAD,
  INCR_PC,
  REGR0S,
  REGR1S,
  REGWS,
  OP0S,
  OP1S,
  IRimm,
  MDRS,
 //  slus,
 //  cond,
 clk
);

input clk;
input [15:0] instr;
output MDR_LOAD, REG_LOAD, MAR_LOAD, IR_LOAD, RAM_LOAD, INCR_PC;
output [1:0] MDRS, OP0S, OP1S;
output [12:0] IRimm;
output [2:0] REGWS, REGR0S, REGR1S;

//outputs
reg [12:0] IRimm;
// csig
reg MDR_LOAD, REG_LOAD, MAR_LOAD, INCR_PC, IR_LOAD, RAM_LOAD;

//regsel
reg REGR0S, REGR1S, REGWS;

//bussel
// MDRS: 0: Imm, 1: RAM, 2:ALU
// OP0S/OP1S: 0:R0, 1:R1, 2:MDR
reg [1:0] MDRS, OP0S, OP1S;

// internal registers
reg [3:0] state;
wire [3:0] next_state;

wire [2:0] opc0, tgt;
wire [10:0] imm10;



parameter FETCH = 4'b0001, DECODE = 4'b0010, READ = 4'b0100, EXEC = 4'b1000;

assign next_state = fsm_function(state);

initial begin
  state = 0;
  //reset = 0;
end

function [3:0] fsm_function;
	input [3:0] state;
	case(state)
		FETCH: fsm_function = DECODE;
		DECODE: fsm_function = READ;
		READ: fsm_function = EXEC;
		EXEC: fsm_function = FETCH;
		default: fsm_function = FETCH;
	endcase
endfunction

always @(posedge clk)
begin
	state <= #1 next_state;
end

// Opcode & Immediate splits
assign opc0 = instr[15:13];
assign imm10 = instr[12:3];
assign tgt = instr[2:0];


always @*
// To synthesize combinational logic using an always block, all inputs to the design must appear in the sensitivity list.
begin
  // Immediate mux
  case(opc0)
    3'b101: IRimm = imm10;
    default: IRimm = 0;
  endcase

  // reset csig and bussel?
  MDR_LOAD = 0;
  MAR_LOAD = 0;
  REG_LOAD = 0;
  IR_LOAD = 0;
  INCR_PC = 0;
  // generate csig and bussel
  case(state)
    FETCH:
      begin
        MDRS = 0;
        OP0S = 0;
        //OP1S = 0;
        REGR0S = 0;
        //REGR1S = 0;

        REGR1S = 3'b111;
        OP1S = 2'b01;
        MAR_LOAD = 1'b1;
        INCR_PC = 1'b1;
        IR_LOAD = 1'b1;
      end
    DECODE:
      begin
        case(opc0)
          3'b101:
            begin
              MDRS = 2'b00;
              OP0S = 2'b10;
              MDR_LOAD = 1'b1;
            end
        endcase
      end
    EXEC:
      begin
        case(opc0)
          3'b101:
            begin
              OP0S = 2'b10;
              REGWS = tgt;
              REG_LOAD = 1'b1;
            end
        endcase
      end
  endcase
end


endmodule

cpu.v

module cpu (
  // reset,
  RAMin,
  RAMout,
  we,
  RAMaddr,
  clk
);

// i/o
input clk;
input [15:0] RAMout;
output we;
output [15:0] RAMin, RAMaddr;

wire [1:0] op0s, op1s, mdrs;
wire [12:0] IRimm;
wire [2:0]  regr0s, regr1s, regws;
wire [15:0] IRout;

decoder decoder (
  .instr      (RAMout),
  .MDR_LOAD   (mdr_load),
  .MAR_LOAD   (mar_load),
  .REG_LOAD   (reg_load),
  .RAM_LOAD   (ram_load),
  .IR_LOAD    (ir_load),
  .INCR_PC    (incr_pc),
  .OP0S       (op0s),
  .OP1S       (op1s),
  .IRimm      (IRimm),
  .MDRS       (mdrs),
  .REGR0S     (regr0s),
  .REGR1S     (regr1s),
  .REGWS      (regws),
  .clk        (clk)
);


// SYSREGS
// register(in, reset, load, clk, out)
wire [15:0] MDRout, MARin, MARout, IRin;
reg [15:0] MDRin;

register MDR (
  .in     (MDRin),
  .reset  (reset),
  .load   (mdr_load),
  .clk    (clk),
  .out    (MDRout)
);

register MAR (
  .in     (MARin),
  .reset  (reset),
  .load   (mar_load),
  .clk    (clk),
  .out    (MARout)
);

register_posedge IR (
  .in     (RAMout),
  .reset  (reset),
  .load   (ir_load),
  .clk    (clk),
  .out    (IRout)
);

// REGFILE

wire [15:0] regr0, regr1, regw;

regfile regfile (
  .regr0  (regr0),
  .regr1  (regr1),
  .regw   (regw),
  .regr0s (regr0s),
  .regr1s (regr1s),
  .regws  (regws),
  .we     (reg_load),
  .incr_pc  (incr_pc),
  .clk    (clk)
);

// ALU
wire [15:0] ALUout;
wire [2:0] f;
reg [15:0] op0, op1;

alu alu (
  .x          (op0),
  .y          (op1),
  .f          (f),
  .out        (ALUout)
);

assign regw = ALUout;
assign MARin = ALUout;
assign RAMin = MDRout;
assign we = ram_load;
assign RAMaddr = MARout;

// bussel muxes
// MDRS: 0: Imm, 1: RAM, 2:ALU
// OP0S/OP1S: 0:R0, 1:R1, 2:MDR
always @* begin

  case(mdrs)
  2'b00: MDRin = IRimm;
  //2'b01: MDRin = RAMout;
  2'b10: MDRin = ALUout;
  endcase

  case(op0s)
  2'b00: op0 = regr0;
  2'b01: op0 = regr1;
  2'b10: op0 = MDRout;
  endcase

  case(op1s)
  2'b00: op1 = regr0;
  2'b01: op1 = regr1;
  2'b10: op1 = MDRout;
  endcase
end

endmodule

computer.v
// Computer

module computer (
  clk
);

input clk;

wire [15:0] RAMin, RAMout, RAMaddr;
wire we;

cpu cpu (
  .RAMin (RAMin),
  .RAMout (RAMout),
  .RAMaddr  (RAMaddr),
  .we  (we),
  .clk (clk)
);

ram ram (
  .data_out (RAMout),
  .data_in  (RAMin),
  .address  (RAMaddr),
  .we       (we),
  .clk      (clk)
);

endmodule

computer_tb.v
module computer_tb;
  reg clk, reset;

computer U0 (
  .clk    (clk)
  );

  initial begin
    clk = 0;
    reset = 0;
  end

  always
    #5 clk = !clk;

  initial  begin
    $dumpfile ("computer.vcd");
    $dumpvars;
  end

  initial  begin
    $display("\t\ttime,\tclk,\ticycle");
    //$monitor("%d,\t%b,\t%b",$time, clk,reset);
  end

  initial
  #100 $finish;

  //Rest of testbench code after this line

endmodule

computer.vcd
$date
	Sun Feb 26 19:25:22 2017
$end
$version
	Icarus Verilog
$end
$timescale
	1s
$end
$scope module computer_tb $end
$var reg 1 ! clk $end
$var reg 1 " reset $end
$scope module U0 $end
$var wire 1 ! clk $end
$var wire 1 # we $end
$var wire 16 $ RAMout [15:0] $end
$var wire 16 % RAMin [15:0] $end
$var wire 16 & RAMaddr [15:0] $end
$scope module cpu $end
$var wire 16 ' MARin [15:0] $end
$var wire 16 ( RAMaddr [15:0] $end
$var wire 16 ) RAMin [15:0] $end
$var wire 1 ! clk $end
$var wire 3 * f [2:0] $end
$var wire 16 + regw [15:0] $end
$var wire 1 , reset $end
$var wire 1 # we $end
$var wire 3 - regws [2:0] $end
$var wire 3 . regr1s [2:0] $end
$var wire 16 / regr1 [15:0] $end
$var wire 3 0 regr0s [2:0] $end
$var wire 16 1 regr0 [15:0] $end
$var wire 1 2 reg_load $end
$var wire 1 3 ram_load $end
$var wire 2 4 op1s [1:0] $end
$var wire 2 5 op0s [1:0] $end
$var wire 2 6 mdrs [1:0] $end
$var wire 1 7 mdr_load $end
$var wire 1 8 mar_load $end
$var wire 1 9 ir_load $end
$var wire 1 : incr_pc $end
$var wire 16 ; RAMout [15:0] $end
$var wire 16 < MDRout [15:0] $end
$var wire 16 = MARout [15:0] $end
$var wire 16 > IRout [15:0] $end
$var wire 13 ? IRimm [12:0] $end
$var wire 16 @ ALUout [15:0] $end
$var reg 16 A MDRin [15:0] $end
$var reg 16 B op0 [15:0] $end
$var reg 16 C op1 [15:0] $end
$scope module IR $end
$var wire 1 ! clk $end
$var wire 1 , reset $end
$var wire 1 9 load $end
$var wire 16 D in [15:0] $end
$var reg 16 E out [15:0] $end
$upscope $end
$scope module MAR $end
$var wire 1 ! clk $end
$var wire 16 F in [15:0] $end
$var wire 1 , reset $end
$var wire 1 8 load $end
$var reg 16 G out [15:0] $end
$upscope $end
$scope module MDR $end
$var wire 1 ! clk $end
$var wire 16 H in [15:0] $end
$var wire 1 , reset $end
$var wire 1 7 load $end
$var reg 16 I out [15:0] $end
$upscope $end
$scope module alu $end
$var wire 3 J f [2:0] $end
$var wire 16 K x [15:0] $end
$var wire 16 L y [15:0] $end
$var reg 16 M out [15:0] $end
$upscope $end
$scope module decoder $end
$var wire 1 ! clk $end
$var wire 3 N tgt [2:0] $end
$var wire 3 O opc0 [2:0] $end
$var wire 4 P next_state [3:0] $end
$var wire 16 Q instr [15:0] $end
$var wire 11 R imm10 [10:0] $end
$var reg 1 : INCR_PC $end
$var reg 1 9 IR_LOAD $end
$var reg 13 S IRimm [12:0] $end
$var reg 1 8 MAR_LOAD $end
$var reg 2 T MDRS [1:0] $end
$var reg 1 7 MDR_LOAD $end
$var reg 2 U OP0S [1:0] $end
$var reg 2 V OP1S [1:0] $end
$var reg 1 3 RAM_LOAD $end
$var reg 3 W REGR0S [2:0] $end
$var reg 3 X REGR1S [2:0] $end
$var reg 3 Y REGWS [2:0] $end
$var reg 1 2 REG_LOAD $end
$var reg 4 Z state [3:0] $end
$scope function fsm_function $end
$var reg 4 [ fsm_function [3:0] $end
$var reg 4 \ state [3:0] $end
$upscope $end
$upscope $end
$scope module regfile $end
$var wire 1 ! clk $end
$var wire 1 : incr_pc $end
$var wire 3 ] regr0s [2:0] $end
$var wire 3 ^ regr1s [2:0] $end
$var wire 16 _ regw [15:0] $end
$var wire 3 ` regws [2:0] $end
$var wire 1 2 we $end
$var reg 16 a R1 [15:0] $end
$var reg 16 b R2 [15:0] $end
$var reg 16 c R3 [15:0] $end
$var reg 16 d R4 [15:0] $end
$var reg 16 e R5 [15:0] $end
$var reg 16 f R6 [15:0] $end
$var reg 16 g R7 [15:0] $end
$var reg 16 h regr0 [15:0] $end
$var reg 16 i regr1 [15:0] $end
$upscope $end
$upscope $end
$scope module ram $end
$var wire 16 j address [15:0] $end
$var wire 1 ! clk $end
$var wire 16 k data_in [15:0] $end
$var wire 1 # we $end
$var wire 16 l data_out [15:0] $end
$upscope $end
$upscope $end
$upscope $end
$enddefinitions $end
#0
$dumpvars
bx l
bx k
bx j
bx i
b0 h
b0 g
bx f
bx e
bx d
bx c
bx b
bx a
bx `
bx _
bx ^
bx ]
b0 \
b1 [
b0 Z
bx Y
bx X
bx W
bx V
bx U
bx T
b0 S
b0xxxxxxxxxx R
bx Q
b1 P
bx O
bx N
bx M
bx L
bx K
bz J
bx I
bx H
bx G
bx F
bx E
bx D
bx C
bx B
bx A
bx @
b0 ?
bx >
bx =
bx <
bx ;
0:
09
08
07
bx 6
bx 5
bx 4
x3
02
b0 1
bx 0
bx /
bx .
bx -
z,
bx +
bz *
bx )
bx (
bx '
bx &
bx %
bx $
x#
0"
0!
$end
#5
1!
#6
b0 '
b0 F
b0 +
b0 _
b0 @
b0 M
b0 C
b0 L
b0 /
b0 i
b0 B
b0 K
b0 A
b0 H
19
1:
18
b1 4
b1 V
b111 .
b111 X
b111 ^
b0 0
b0 W
b0 ]
b0 5
b0 U
b0 6
b0 T
b10 P
b10 [
b1 \
b1 Z
#10
b10 '
b10 F
b10 +
b10 _
b10 @
b10 M
b10 C
b10 L
b1100100 A
b1100100 H
1:
19
18
b1100100 ?
b1100100 S
b10 /
b10 i
b101 O
b10 N
b1100100 R
b10 g
b1010001100100010 $
b1010001100100010 ;
b1010001100100010 D
b1010001100100010 Q
b1010001100100010 l
b0 &
b0 (
b0 j
b0 =
b0 G
0!
#15
b1010001100100010 >
b1010001100100010 E
1!
#16
bx '
bx F
bx +
bx _
bx @
bx M
bx B
bx K
17
b10 5
b10 U
0:
09
08
b100 P
b100 [
b10 \
b10 Z
#20
b1100110 '
b1100110 F
b1100110 +
b1100110 _
b1100110 @
b1100110 M
b1100100 B
b1100100 K
b1100100 %
b1100100 )
b1100100 k
b1100100 <
b1100100 I
0!
#25
1!
#26
07
b1000 P
b1000 [
b100 \
b100 Z
#30
0!
#35
1!
#36
12
b10 -
b10 Y
b10 `
b1 P
b1 [
b1000 \
b1000 Z
#40
b1100110 b
0!
#45
1!
#46
b10 '
b10 F
b10 +
b10 _
b10 @
b10 M
b0 B
b0 K
19
1:
18
b0 5
b0 U
02
b10 P
b10 [
b1 \
b1 Z
#50
b100 '
b100 F
b100 +
b100 _
b100 @
b100 M
b100 C
b100 L
b1000100 A
b1000100 H
1:
19
18
b1000100 ?
b1000100 S
b100 /
b100 i
b1000100 R
b100 N
b100 g
b1010001000100100 $
b1010001000100100 ;
b1010001000100100 D
b1010001000100100 Q
b1010001000100100 l
b10 &
b10 (
b10 j
b10 =
b10 G
0!
#55
b1010001000100100 >
b1010001000100100 E
1!
#56
b1101000 '
b1101000 F
b1101000 +
b1101000 _
b1101000 @
b1101000 M
b1100100 B
b1100100 K
17
b10 5
b10 U
0:
09
08
b100 P
b100 [
b10 \
b10 Z
#60
b1001000 '
b1001000 F
b1001000 +
b1001000 _
b1001000 @
b1001000 M
b1000100 B
b1000100 K
b1000100 %
b1000100 )
b1000100 k
b1000100 <
b1000100 I
0!
#65
1!
#66
07
b1000 P
b1000 [
b100 \
b100 Z
#70
0!
#75
1!
#76
12
b100 -
b100 Y
b100 `
b1 P
b1 [
b1000 \
b1000 Z
#80
b1001000 d
0!
#85
1!
#86
b100 '
b100 F
b100 +
b100 _
b100 @
b100 M
b0 B
b0 K
19
1:
18
b0 5
b0 U
02
b10 P
b10 [
b1 \
b1 Z
#90
b110 '
b110 F
b110 +
b110 _
b110 @
b110 M
b110 C
b110 L
b0 A
b0 H
1:
19
18
b0 ?
b0 S
b110 /
b110 i
bx O
bx N
b0xxxxxxxxxx R
b110 g
bx $
bx ;
bx D
bx Q
bx l
b100 &
b100 (
b100 j
b100 =
b100 G
0!
#95
bx >
bx E
1!
#96
0:
09
08
b100 P
b100 [
b10 \
b10 Z
