ALU.v
module alu(
  x,y,
  f,
  out
);

  input       [15:0]  x,y;
  input       [2:0]   f;
  output      [15:0]  out;

  reg [15:0] out;


  always @* begin

    case(f)
      3'b000: out = x + y;
      3'b001: out = x - y;
			3'b010: out = x & y;
			3'b011: out = x | y;
			3'b110: out = (x << 9) | (y & 16'h1ff);
      default: out = x + y;
    endcase
  end

endmodule

regfile.v
// Regfile proof of concept
//

module regfile (
regr0,
regr1,
regw,
regr0s,
regr1s,
regws,
we,
incr_pc,
clk
);

input [15:0] regw;
input [2:0] regr0s, regr1s, regws;
input we, clk, incr_pc;
output [15:0] regr0, regr1;

reg [15:0] regr0, regr1;

reg [15:0] R1;
reg [15:0] R2 = 15'b101010101010101;
reg [15:0] R3;
reg [15:0] R4;
reg [15:0] R5;
reg [15:0] R6;
reg [15:0] R7 = 0;


always @(negedge clk)
begin
	case(regr0s)
	3'b000: regr0 <= 0;
	3'b001: regr0 <= R1;
	3'b010: regr0 <= R2;
	3'b011: regr0 <= R3;
	3'b100: regr0 <= R4;
	3'b101: regr0 <= R5;
	3'b110: regr0 <= R6;
	3'b111: regr0 <= R7;
  default: regr0 <= 0;
	endcase

	case(regr1s)
	3'b000: regr1 <= 0;
	3'b001: regr1 <= R1;
	3'b010: regr1 <= R2;
	3'b011: regr1 <= R3;
	3'b100: regr1 <= R4;
	3'b101: regr1 <= R5;
	3'b110: regr1 <= R6;
	3'b111: regr1 <= R7;
  default: regr0 <= 0;
	endcase

	if (we) begin
		case(regws)
		3'b001: R1 <= regw;
		3'b010: R2 <= regw;
		3'b011: R3 <= regw;
		3'b100: R4 <= regw;
		3'b101: R5 <= regw;
		3'b110: R6 <= regw;
		3'b111: R7 <= regw;
		endcase
	end

	// PC should auto increment always (?)
	if (incr_pc) begin
    R7 <= R7 + 2;
  end

end
endmodule

register.v
module register(
in, reset, load, clk, out
);

input [15:0] in;
input load, reset, clk;
output [15:0] out;

reg [15:0] out = 0;

always @(negedge clk)
begin

if (reset && load)
	out = 0;
else if (reset)
	out = 0;
else if (load)
	out = in;
end

endmodule

decoder.v
// decoder - proof of concept
//

module decoder (
  // instr,
 //  mar_load,
 //  ir_load,
  MDR_LOAD,
  REG_LOAD,
//  ram_load,
 //  regr0s,
 //  regr1s,
  REGWS,
  OP0S,
  OP1S,
  IRimm,
  MDRS,
 //  slus,
 //  cond,
 clk
);

input clk;
output MDR_LOAD, REG_LOAD;
output [1:0] MDRS, OP0S, OP1S;
output [12:0] IRimm;
output [2:0] REGWS;

//outputs
reg [12:0] IRimm;
// csig
reg MDR_LOAD, REG_LOAD;

//regsel
reg REGR0S, REGR1S, REGWS;

//bussel
// MDRS: 0: Imm, 1: RAM, 2:ALU
// OP0S/OP1S: 0:R0, 1:R1, 2:MDR
reg [1:0] MDRS, OP0S, OP1S;

// internal registers
reg [15:0] instr = 16'b1010001100100010;

reg [3:0] state;
wire [3:0] next_state;

wire [2:0] opc0, tgt;
wire [10:0] imm10;



parameter FETCH = 4'b0001, DECODE = 4'b0010, READ = 4'b0100, EXEC = 4'b1000;

assign next_state = fsm_function(state);


function [3:0] fsm_function;
	input [3:0] state;
	case(state)
		FETCH: fsm_function = DECODE;
		DECODE: fsm_function = READ;
		READ: fsm_function = EXEC;
		EXEC: fsm_function = FETCH;
		default: fsm_function = FETCH;
	endcase
endfunction

always @(posedge clk)
begin
	state <= #1 next_state;
end

// Opcode & Immediate splits
assign opc0 = instr[15:13];
assign imm10 = instr[12:3];
assign tgt = instr[2:0];


always @*
// To synthesize combinational logic using an always block, all inputs to the design must appear in the sensitivity list.
begin
  // Immediate mux
  case(opc0)
    3'b101: IRimm = imm10;
    default: IRimm = 0;
  endcase

  // reset csig and bussel?
  MDR_LOAD = 0;
  REG_LOAD = 0;
  // generate csig and bussel
  case(state)
    FETCH:
      begin
        MDRS = 0;
        OP0S = 0;
        OP1S = 0;
        REGR0S = 0;
        REGR1S = 0;
      end
    DECODE:
      begin
        case(opc0)
          3'b101:
            begin
              MDRS = 2'b00;
              OP0S = 2'b10;
              MDR_LOAD = 1'b1;
            end
        endcase
      end
    EXEC:
      begin
        case(opc0)
          3'b101:
            begin
              OP0S = 2'b10;
              REGWS = tgt;
              REG_LOAD = 1'b1;
            end
        endcase
      end
  endcase
end


endmodule

cpu.v

module cpu (
  // reset,
//   RAMin,
//   RAMout,
//we,
  clk
);

// i/o
input clk;

wire [1:0] op0s, op1s, mdrs;
wire [12:0] IRimm;
wire [2:0]  regr0s, regr1s, regws;

decoder decoder (
  .MDR_LOAD   (mdr_load),
  .REG_LOAD   (reg_load),
  .OP0S       (op0s),
  .OP1S       (op1s),
  .IRimm      (IRimm),
  .MDRS       (mdrs),
  .REGWS      (regws),
  .clk        (clk)
);


// SYSREGS
// register(in, reset, load, clk, out)
wire [15:0] MDRout, MARin, MARout, IRin, IRout, RAMin;
reg [15:0] MDRin;

register MDR (
  .in     (MDRin),
  .reset  (reset),
  .load   (mdr_load),
  .clk    (clk),
  .out    (MDRout)
);

register MAR (
  .in     (MARin),
  .reset  (reset),
  .load   (mar_load),
  .clk    (clk),
  .out    (MARout)
);

register IR (
  .in     (RAMin),
  .reset  (reset),
  .load   (ir_load),
  .clk    (clk),
  .out    (IRout)
);

// REGFILE

wire [15:0] regr0, regr1, regw;

regfile regfile (
  .regr0  (regr0),
  .regr1  (regr1),
  .regw   (regw),
  .regr0s (regr0s),
  .regr1s (regr1s),
  .regws  (regws),
  .we     (reg_load),
  .incr_pc  (incr_pc),
  .clk    (clk)
);

// ALU
wire [15:0] ALUout;
wire [2:0] f;
reg [15:0] op0, op1;

alu alu (
  .x          (op0),
  .y          (op1),
  .f          (f),
  .out        (ALUout)
);

assign regw = ALUout;

// bussel muxes
// MDRS: 0: Imm, 1: RAM, 2:ALU
// OP0S/OP1S: 0:R0, 1:R1, 2:MDR
always @* begin

  case(mdrs)
  2'b00: MDRin = IRimm;
  //2'b01: MDRin = RAMout;
  2'b10: MDRin = ALUout;
  endcase

  case(op0s)
  2'b00: op0 = regr0;
  2'b01: op0 = regr1;
  2'b10: op0 = MDRout;
  endcase

  case(op1s)
  2'b00: op1 = regr0;
  2'b01: op1 = regr1;
  2'b10: op1 = MDRout;
  endcase
end

endmodule

cpu_tb.v
module cpu_tb;
  reg clk, reset;

cpu U0 (
  .clk    (clk)
  );

  initial begin
    clk = 0;
    reset = 0;
  end

  always
    #5 clk = !clk;

  initial  begin
    $dumpfile ("cpu.vcd");
    $dumpvars;
  end

  initial  begin
    $display("\t\ttime,\tclk,\ticycle");
    //$monitor("%d,\t%b,\t%b",$time, clk,reset);
  end

  initial
  #100 $finish;

  //Rest of testbench code after this line

endmodule

cpu.vcd
$date
	Sun Feb 26 10:36:59 2017
$end
$version
	Icarus Verilog
$end
$timescale
	1s
$end
$scope module cpu_tb $end
$var reg 1 ! clk $end
$var reg 1 " reset $end
$scope module U0 $end
$var wire 16 # MARin [15:0] $end
$var wire 16 $ RAMin [15:0] $end
$var wire 1 ! clk $end
$var wire 3 % f [2:0] $end
$var wire 1 & incr_pc $end
$var wire 1 ' ir_load $end
$var wire 1 ( mar_load $end
$var wire 3 ) regr0s [2:0] $end
$var wire 3 * regr1s [2:0] $end
$var wire 16 + regw [15:0] $end
$var wire 1 , reset $end
$var wire 3 - regws [2:0] $end
$var wire 16 . regr1 [15:0] $end
$var wire 16 / regr0 [15:0] $end
$var wire 1 0 reg_load $end
$var wire 2 1 op1s [1:0] $end
$var wire 2 2 op0s [1:0] $end
$var wire 2 3 mdrs [1:0] $end
$var wire 1 4 mdr_load $end
$var wire 16 5 MDRout [15:0] $end
$var wire 16 6 MARout [15:0] $end
$var wire 16 7 IRout [15:0] $end
$var wire 13 8 IRimm [12:0] $end
$var wire 16 9 ALUout [15:0] $end
$var reg 16 : MDRin [15:0] $end
$var reg 16 ; op0 [15:0] $end
$var reg 16 < op1 [15:0] $end
$scope module IR $end
$var wire 1 ! clk $end
$var wire 16 = in [15:0] $end
$var wire 1 ' load $end
$var wire 1 , reset $end
$var reg 16 > out [15:0] $end
$upscope $end
$scope module MAR $end
$var wire 1 ! clk $end
$var wire 16 ? in [15:0] $end
$var wire 1 ( load $end
$var wire 1 , reset $end
$var reg 16 @ out [15:0] $end
$upscope $end
$scope module MDR $end
$var wire 1 ! clk $end
$var wire 16 A in [15:0] $end
$var wire 1 , reset $end
$var wire 1 4 load $end
$var reg 16 B out [15:0] $end
$upscope $end
$scope module alu $end
$var wire 3 C f [2:0] $end
$var wire 16 D x [15:0] $end
$var wire 16 E y [15:0] $end
$var reg 16 F out [15:0] $end
$upscope $end
$scope module decoder $end
$var wire 1 ! clk $end
$var wire 3 G tgt [2:0] $end
$var wire 3 H opc0 [2:0] $end
$var wire 4 I next_state [3:0] $end
$var wire 11 J imm10 [10:0] $end
$var reg 13 K IRimm [12:0] $end
$var reg 2 L MDRS [1:0] $end
$var reg 1 4 MDR_LOAD $end
$var reg 2 M OP0S [1:0] $end
$var reg 2 N OP1S [1:0] $end
$var reg 1 O REGR0S $end
$var reg 1 P REGR1S $end
$var reg 3 Q REGWS [2:0] $end
$var reg 1 0 REG_LOAD $end
$var reg 16 R instr [15:0] $end
$var reg 4 S state [3:0] $end
$scope function fsm_function $end
$var reg 4 T fsm_function [3:0] $end
$var reg 4 U state [3:0] $end
$upscope $end
$upscope $end
$scope module regfile $end
$var wire 1 ! clk $end
$var wire 1 & incr_pc $end
$var wire 3 V regr0s [2:0] $end
$var wire 3 W regr1s [2:0] $end
$var wire 16 X regw [15:0] $end
$var wire 3 Y regws [2:0] $end
$var wire 1 0 we $end
$var reg 16 Z R1 [15:0] $end
$var reg 16 [ R2 [15:0] $end
$var reg 16 \ R3 [15:0] $end
$var reg 16 ] R4 [15:0] $end
$var reg 16 ^ R5 [15:0] $end
$var reg 16 _ R6 [15:0] $end
$var reg 16 ` R7 [15:0] $end
$var reg 16 a regr0 [15:0] $end
$var reg 16 b regr1 [15:0] $end
$upscope $end
$upscope $end
$upscope $end
$enddefinitions $end
#0
$dumpvars
bx b
b0 a
b0 `
bx _
bx ^
bx ]
bx \
b101010101010101 [
bx Z
bx Y
bx X
bz W
bz V
bx U
b1 T
bx S
b1010001100100010 R
bx Q
xP
xO
bx N
bx M
bx L
b1100100 K
b1100100 J
b1 I
b101 H
b10 G
bx F
bx E
bx D
bz C
b0 B
bx A
b0 @
bz ?
b0 >
bz =
bx <
bx ;
bx :
bx 9
b1100100 8
b0 7
b0 6
b0 5
04
bx 3
bx 2
bx 1
00
b0 /
bx .
bx -
z,
bx +
bz *
bz )
z(
z'
z&
bz %
bz $
bz #
0"
0!
$end
#5
1!
#6
b0 +
b0 X
b0 9
b0 F
b0 <
b0 E
b0 ;
b0 D
b1100100 :
b1100100 A
0P
0O
b0 1
b0 N
b0 2
b0 M
b0 3
b0 L
b10 I
b10 T
b1 U
b1 S
#10
0!
#15
1!
#16
14
b10 2
b10 M
b100 I
b100 T
b10 U
b10 S
#20
b1100100 +
b1100100 X
b1100100 9
b1100100 F
b1100100 ;
b1100100 D
b1100100 5
b1100100 B
0!
#25
1!
#26
04
b1000 I
b1000 T
b100 U
b100 S
#30
0!
#35
1!
#36
10
b10 -
b10 Q
b10 Y
b1 I
b1 T
b1000 U
b1000 S
#40
b1100100 [
0!
#45
1!
#46
b0 +
b0 X
b0 9
b0 F
b0 ;
b0 D
b0 2
b0 M
00
b10 I
b10 T
b1 U
b1 S
#50
0!
#55
1!
#56
b1100100 +
b1100100 X
b1100100 9
b1100100 F
b1100100 ;
b1100100 D
14
b10 2
b10 M
b100 I
b100 T
b10 U
b10 S
#60
0!
#65
1!
#66
04
b1000 I
b1000 T
b100 U
b100 S
#70
0!
#75
1!
#76
10
b1 I
b1 T
b1000 U
b1000 S
#80
0!
#85
1!
#86
b0 +
b0 X
b0 9
b0 F
b0 ;
b0 D
b0 2
b0 M
00
b10 I
b10 T
b1 U
b1 S
#90
0!
#95
1!
#96
b1100100 +
b1100100 X
b1100100 9
b1100100 F
b1100100 ;
b1100100 D
14
b10 2
b10 M
b100 I
b100 T
b10 U
b10 S
