ti16450.v
//
// 16450 compatible UART with synchronous bus interface
// rclk/baudout is clk enable instead of actual clock
//
// Copyright (c) 2005 Guy Hutchison (ghutchis@opencores.org)
// Based on VHDL 16450 UART by Daniel Wallner
//
// Permission is hereby granted, free of charge, to any person obtaining a
// copy of this software and associated documentation files (the "Software"),
// to deal in the Software without restriction, including without limitation
// the rights to use, copy, modify, merge, publish, distribute, sublicense,
// and/or sell copies of the Software, and to permit persons to whom the
// Software is furnished to do so, subject to the following conditions:
//
// The above copyright notice and this permission notice shall be included
// in all copies or substantial portions of the Software.
//
// THE SOFTWARE IS PROVIDED "AS IS", WITHOUT WARRANTY OF ANY KIND,
// EXPRESS OR IMPLIED, INCLUDING BUT NOT LIMITED TO THE WARRANTIES OF
// MERCHANTABILITY, FITNESS FOR A PARTICULAR PURPOSE AND NONINFRINGEMENT.
// IN NO EVENT SHALL THE AUTHORS OR COPYRIGHT HOLDERS BE LIABLE FOR ANY
// CLAIM, DAMAGES OR OTHER LIABILITY, WHETHER IN AN ACTION OF CONTRACT,
// TORT OR OTHERWISE, ARISING FROM, OUT OF OR IN CONNECTION WITH THE
// SOFTWARE OR THE USE OR OTHER DEALINGS IN THE SOFTWARE.

module T16450
  (
   input reset_n,
   input clk,
   input rclk,
   input cs_xn,
   input rd_n,
   input wr_n,
   input [2:0] addr,
   input [7:0] wr_data,
   output reg [7:0] rd_data,
   input sin,
   input cts_n,
   input dsr_n,
   input ri_n,
   input dcd_n,
   output reg sout,
   output reg rts_n,
   output reg dtr_n,
   output reg out1_n,
   output reg out2_n,
   output reg baudout,
   output reg intr
   );

  reg [7:0] RBR;        // Reciever Buffer Register
  reg [7:0] THR;        // Transmitter Holding Register
  reg [7:0] IER;        // Interrupt Enable Register
  reg [7:0] IIR;        // Interrupt Ident. Register
  reg [7:0] LCR;        // Line Control Register
  reg [7:0] MCR;        // MODEM Control Register
  reg [7:0] LSR;        // Line Status Register
  reg [7:0] MSR;        // MODEM Status Register
  reg [7:0] SCR;        // Scratch Register
  reg [7:0] DLL;        // Divisor Latch (LS)
  reg [7:0] DLM;        // Divisor Latch (MS)

  reg [7:0] DM0;
  reg [7:0] DM1;

  reg [3:0] MSR_In;

  reg [3:0] Bit_Phase;
  reg [3:0] Brk_Cnt;
  reg       RX_Filtered;
  reg [7:0] RX_ShiftReg;
  reg [3:0] RX_Bit_Cnt;
  reg       RX_Parity;
  reg       RXD;

  reg       TX_Tick;
  reg [7:0] TX_ShiftReg;
  reg [3:0] TX_Bit_Cnt;
  reg       TX_Parity;
  reg       TX_Next_Is_Stop;
  reg       TX_Stop_Bit;
  reg       TXD;

  always @*
    begin
      dtr_n = MCR[4] || ~ MCR[0];
      rts_n = MCR[4] || ~ MCR[1];
      out1_n = MCR[4] || ~ MCR[2];
      out2_n = MCR[4] || ~ MCR[3];
      sout = MCR[4] || (TXD && ~ LCR[6]);
      if (!MCR[4]) RXD = sin;
      else RXD = (TXD && !LCR[6]);

      intr = ~IIR[0];

      if (LCR[7])
        begin
          DM0 = DLL;
          DM1 = DLM;
        end
      else
        begin
          DM0 = RBR;
          DM1 = IER;
        end

      case (addr)
        3'h0 : rd_data = DM0;
        3'h1 : rd_data = DM1;
        3'h2 : rd_data = IIR;
        3'h3 : rd_data = LCR;
        3'h4 : rd_data = MCR;
        3'h5 : rd_data = LSR;
        3'h6 : rd_data = MSR;
        default : rd_data = SCR;
      endcase
    end

  always @ (posedge clk)
    begin
      if (!reset_n)
        begin
          THR <= #1 8'b00000000;
          IER <= #1 8'b00000000;
          LCR <= #1 8'b00000000;
          MCR <= #1 8'b00000000;
          MSR[3:0] <= #1 4'b0000;
          SCR <= #1 8'b00000000;
          DLL <= #1 8'b00000000;
          DLM <= #1 8'b00000000;
        end
      else
        begin
          if (!wr_n && !cs_n )
            begin
              case (addr)
                3'b000  :
                  begin
                    if (LCR[7])
                      DLL <= #1 wr_data;
                    else
                      THR <= #1 wr_data;
                  end
                3'b001  :
                  begin
                    if (LCR[7])
                      DLM <= #1 wr_data;
                    else
                      IER[3:0] <= #1 wr_data[3:0];
                  end
                3'b011  : LCR <= #1 wr_data;
                3'b100  : MCR <= #1 wr_data;
                3'b111  : SCR <= #1 wr_data;
                default : ;
              endcase
            end
          if (!rd_n && !cs_n && (addr == 3'b110))
            MSR[3:0] <= #1 4'b0000;
          if (MSR[4] != MSR_In[0])
            MSR[0] <= #1 1'b1;
          if (MSR[5] != MSR_In[1])
            MSR[1] <= #1 1'b1;
          if (!MSR[6] && MSR_In[2])
            MSR[2] <= #1 1'b1;
          if (MSR[7] != MSR_In[3])
            MSR[3] <= #1 1'b1;
        end
    end
  always @ (posedge clk)
    begin
      if (!MCR[4])
        begin
          MSR[4] <= #1 MSR_In[0];
          MSR[5] <= #1 MSR_In[1];
          MSR[6] <= #1 MSR_In[2];
          MSR[7] <= #1 MSR_In[3];
        end
      else
        begin
          MSR[4] <= #1 MCR[1];
          MSR[5] <= #1 MCR[0];
          MSR[6] <= #1 MCR[2];
          MSR[7] <= #1 MCR[3];
        end
      MSR_In[0] <= #1 cts_n;
      MSR_In[1] <= #1 dsr_n;
      MSR_In[2] <= #1 ri_n;
      MSR_In[3] <= #1 dcd_n;
    end

  always @*
    begin
      IIR[7:3] = #1 5'b00000;
      if (IER[2] && (LSR[4:1] != 4'b0000))
        IIR[2:0] = #1 3'b110;
      else if (IER[0] && LSR[0])
        IIR[2:0] = #1 3'b100;
      else if (IER[1] && LSR[5])
        IIR[2:0] = #1 3'b010;
      else if (IER[3] && ((!MCR[4] && (MSR[3:0] != 0)) || (MCR[4] && (MCR[3:0] != 0))))
        IIR[2:0] = #1 3'b000;
      else
        IIR[2:0] = #1 3'b001;
    end

  // Baud x 16 clock generator
  always @ (posedge clk)
    begin : clk_gen
      reg [15:0] Baud_Cnt;
      if (!reset_n)
        begin
          Baud_Cnt = 16'b0000000000000000;
          baudout <= #1 1'b0;
        end
      else
        begin
          if ((Baud_Cnt[15:1] == 15'h0) ||
              (!wr_n && !cs_n && (addr[2:1] == 2'b00) && LCR[7]) )
            begin
              Baud_Cnt[15:8] = DLM;
              Baud_Cnt[7:0] = DLL;
              baudout <= #1 1'b1;
            end
          else
            begin
              Baud_Cnt = Baud_Cnt - 1;
              baudout <= #1 1'b0;
            end
        end
    end

  // Input filter
  always @ (posedge clk)
    begin : input_filter
      reg [1:0] Samples;
      if (!reset_n)
        begin
          Samples = 2'b11;
          RX_Filtered <= #1 1'b1;
        end
      else
        begin
          if (rclk)
            begin
              Samples[1] = Samples[0];
              Samples[0] = RXD;
            end
          if (Samples == 2'b00)
            begin
              RX_Filtered <= #1 1'b0;
            end
          if (Samples == 2'b11)
            begin
              RX_Filtered <= #1 1'b1;
            end
        end
    end

  // Receive state machine
  always @ (posedge clk)
    begin
      if (!reset_n)
        begin
          RBR <= #1 8'b00000000;
          LSR[4:0] <= #1 5'b00000;
          Bit_Phase <= #1 4'b0000;
          Brk_Cnt <= #1 4'b0000;
          RX_ShiftReg[7:0] <= #1 8'b00000000;
          RX_Bit_Cnt <= #1 0;
          RX_Parity <= #1 1'b0;
        end
      else
        begin
          if (addr == 3'b000 && !LCR[7] && !rd_n && !cs_n )
            begin
              LSR[0] <= #1 1'b0;   // DR
            end
          if (addr == 3'b101 && !rd_n && !cs_n )
            begin
              LSR[4] <= #1 1'b0;   // BI
              LSR[3] <= #1 1'b0;   // FE
              LSR[2] <= #1 1'b0;   // PE
              LSR[1] <= #1 1'b0;   // OE
            end
          if (rclk)
            begin
              if ((RX_Bit_Cnt == 0) && (RX_Filtered || (Bit_Phase == 4'b0111)))
                begin
                  Bit_Phase <= #1 4'b0000;
                end
              else
                begin
                  Bit_Phase <= #1 Bit_Phase + 1;
                end
              if (Bit_Phase == 4'b1111 )
                begin
                  if (RX_Filtered)
                    begin
                      Brk_Cnt <= #1 4'b0000;
                    end
                  else
                    begin
                      Brk_Cnt <= #1 Brk_Cnt + 1;
                    end
                  if (Brk_Cnt == 4'b1100)
                    begin
                      LSR[4] <= #1 1'b1;     // BI
                    end
                end
              if (RX_Bit_Cnt == 0)
                begin
                  if (Bit_Phase == 4'b0111)
                    begin
                      RX_Bit_Cnt <= #1 RX_Bit_Cnt + 1;
                      RX_Parity <= #1 ! LCR[4];    // EPS
                    end
                end
              else if (Bit_Phase == 4'b1111)
                begin
                  RX_Bit_Cnt <= #1 RX_Bit_Cnt + 1;
                  if (RX_Bit_Cnt == 10 )
                    begin // Parity stop bit
                      RX_Bit_Cnt <= #1 0;
                      LSR[0] <= #1 1'b1; // UART Receive complete
                      LSR[3] <= #1 ~RX_Filtered; // Framing error
                    end
                  else if ((RX_Bit_Cnt == 9 && LCR[1:0] == 2'b11) ||
                           (RX_Bit_Cnt == 8 && LCR[1:0] == 2'b10) ||
                           (RX_Bit_Cnt == 7 && LCR[1:0] == 2'b01) ||
                           (RX_Bit_Cnt == 6 && LCR[1:0] == 2'b00) )
                    begin // Stop bit/Parity
                      RX_Bit_Cnt <= #1 0;
                      if (LCR[3])
                        begin   // PEN
                          RX_Bit_Cnt <= #1 10;
                          if (LCR[5])
                            begin       // Stick parity
                              if (RX_Filtered == LCR[4])
                                begin
                                  LSR[2] <= #1 1'b1;
                                end
                            end
                          else
                            begin
                              if (RX_Filtered != RX_Parity)
                                begin
                                  LSR[2] <= #1 1'b1;
                                end
                            end
                        end
                      else
                        begin
                          LSR[0] <= #1 1'b1; // UART Receive complete
                          LSR[3] <= #1 ~RX_Filtered; // Framing error
                        end
                      RBR <= #1 RX_ShiftReg[7:0];
                      LSR[1] <= #1 LSR[0];
                      if (addr == 3'b101 && !rd_n && !cs_n )
                        begin
                          LSR[1] <= #1 1'b0;
                        end
                    end
                  else
                    begin
                      RX_ShiftReg[6:0] <= #1 RX_ShiftReg[7:1];
                      RX_ShiftReg[7] <= #1 RX_Filtered;
                      if (LCR[1:0] == 2'b10)
                        begin
                          RX_ShiftReg[7] <= #1 1'b0;
                          RX_ShiftReg[6] <= #1 RX_Filtered;
                        end
                      if (LCR[1:0] == 2'b01)
                        begin
                          RX_ShiftReg[7] <= #1 1'b0;
                          RX_ShiftReg[6] <= #1 1'b0;
                          RX_ShiftReg[5] <= #1 RX_Filtered;
                        end
                      if (LCR[1:0] == 2'b00)
                        begin
                          RX_ShiftReg[7] <= #1 1'b0;
                          RX_ShiftReg[6] <= #1 1'b0;
                          RX_ShiftReg[5] <= #1 1'b0;
                          RX_ShiftReg[4] <= #1 RX_Filtered;
                        end
                      RX_Parity <= #1 RX_Filtered ^ RX_Parity;
                    end
                end
            end
        end
    end

  // Transmit bit tick
  always @ (posedge clk)
    begin : bit_tick
      reg [4:0] TX_Cnt;
      if (!reset_n)
        begin
          TX_Cnt = 5'b00000;
          TX_Tick <= #1 1'b0;
        end
      else
        begin
          TX_Tick <= #1 1'b0;
          if (rclk)
            begin
              TX_Cnt = TX_Cnt + 1;
              if (LCR[2] && TX_Stop_Bit)
                begin
                  if (LCR[1:0] == 2'b00)
                    begin
                      if (TX_Cnt == 5'b10111)
                        begin
                          TX_Tick <= #1 1'b1;
                          TX_Cnt[3:0] = 4'b0000;
                        end
                    end
                  else
                    begin
                      if (TX_Cnt == 5'b11111)
                        begin
                          TX_Tick <= #1 1'b1;
                          TX_Cnt[3:0] = 4'b0000;
                        end
                    end
                end
              else
                begin
                  TX_Cnt[4] = 1'b1;
                  if (TX_Cnt[3:0] == 4'b1111)
                    begin
                      TX_Tick <= #1 1'b1;
                    end
                end
            end
        end
    end

  // Transmit state machine
  always @ (posedge clk)
    begin
      if (!reset_n)
        begin
          LSR[7:5] <= #1 3'b011;
          TX_Bit_Cnt <= #1 0;
          TX_ShiftReg <= #1 0;
          TXD <= #1 1'b1;
          TX_Parity <= #1 1'b0;
          TX_Next_Is_Stop <= #1 1'b0;
          TX_Stop_Bit <= #1 1'b0;
        end
      else
        begin
          if (TX_Tick == 1'b1)
            begin
              TX_Next_Is_Stop <= #1 1'b0;
              TX_Stop_Bit <= #1 TX_Next_Is_Stop;
              case (TX_Bit_Cnt)
                0  :
                  begin
                    if (!LSR[5])
                      begin     // THRE
                        TX_Bit_Cnt <= #1 1;
                      end
                    TXD <= #1 1'b1;
                  end
                1  : // Start bit
                  begin
                    TX_ShiftReg[7:0] <= #1 THR;
                    LSR[5] <= #1 1'b1;     // THRE
                    TXD <= #1 1'b0;
                    TX_Parity <= #1 ~LCR[4];       // EPS
                    TX_Bit_Cnt <= #1 TX_Bit_Cnt + 1;
                  end
                10  : // Parity bit
                  begin
                    TXD <= #1 TX_Parity;
                    if (LCR[5] == 1'b1 )
                      begin  // Stick parity
                        TXD <= #1 ~LCR[4];
                      end
                    TX_Bit_Cnt <= #1 0;
                    TX_Next_Is_Stop <= #1 1'b1;
                  end
                default :
                  begin
                    TX_Bit_Cnt <= #1 TX_Bit_Cnt + 1;
                    if ((TX_Bit_Cnt == 9 && LCR[1:0] == 2'b11) ||
                        (TX_Bit_Cnt == 8 && LCR[1:0] == 2'b10) ||
                        (TX_Bit_Cnt == 7 && LCR[1:0] == 2'b01) ||
                        (TX_Bit_Cnt == 6 && LCR[1:0] == 2'b00) )
                      begin
                        TX_Bit_Cnt <= #1 0;
                        if (LCR[3] == 1'b1 )
                          begin // PEN
                            TX_Bit_Cnt <= #1 10;
                          end
                        else
                          begin
                            TX_Next_Is_Stop <= #1 1'b1;
                          end
                        LSR[6] <= #1 1'b1; // TEMT
                      end
                    TXD <= #1 TX_ShiftReg[0];
                    TX_ShiftReg[6:0] <= #1 TX_ShiftReg[7:1];
                    TX_Parity <= #1 TX_ShiftReg[0] ^ TX_Parity;
                  end
              endcase
            end
          if (!wr_n && !cs_n && addr == 3'b000 && !LCR[7] )
            begin
              LSR[5] <= #1 1'b0;   // THRE
              LSR[6] <= #1 1'b0;   // TEMT
            end
        end
    end

endmodule

t16450_tb.v
module t16450_tb;
  reg clk, reset;

	reg [7:0] wr_data;
	reg [2:0] addr;
	reg rd_n, wr_n, cs_n, rclk;

	wire [7:0] rd_data;
	wire loop;

t16450 U0 (
  .clk   (clk),
	.reset_n	(reset),
	.rclk  (rclk),
	.addr	(addr),
	.wr_data (wr_data),
	.rd_data (rd_data),
	.rd_n (rd_n),
	.wr_n (wr_n),
	.cs_n (cs_n),
	.baudout (loop)
);

   // input reset_n,
   // input clk,
   // input rclk,
   // input cs_xn,
   // input rd_n,
   // input wr_n,
   // input [2:0] addr,
   // input [7:0] wr_data,
   // output reg [7:0] rd_data,
   // input sin,
   // input cts_n,
   // input dsr_n,
   // input ri_n,
   // input dcd_n,


  initial begin
    clk = 0;
    cs_n = 0; // select uart
		rclk = 1;
		reset = 0;
		#10
		reset = 1;
		#10
		wr_n = 0;
		addr = 3'h1;
		wr_data = 0;
		#10
		addr = 3'h3;
		wr_data = 8'h80;
		#10
		addr = 3'h0;
		wr_data = 8'h01;
		#10
		addr = 3'h1;
		wr_data = 8'h0;
		#10
		addr = 3'h3;
		wr_data = 8'h3;
		#10
		addr = 3'h5;
		wr_data = 8'h20;
		#10
		addr = 3'h0;
		wr_data = 8'h69;
  end

  integer idx;

  always
    #5 clk = !clk;


  initial  begin
    $dumpfile ("t16450.vcd");
    $dumpvars;

  end

  initial  begin
    $display("\t\ttime,\tclk,\ticycle");
    //$monitor("%d,\t%b,\t%b",$time, clk,reset);
  end

  initial
  #50000 $finish;

  //Rest of testbench code after this line

endmodule

t16450.vcd
$date
	Mon Mar 20 19:52:28 2017
$end
$version
	Icarus Verilog
$end
$timescale
	1s
$end
$scope module t16450_tb $end
$var wire 8 ! rd_data [7:0] $end
$var wire 1 " loop $end
$var reg 3 # addr [2:0] $end
$var reg 1 $ clk $end
$var reg 1 % cs_n $end
$var reg 1 & rclk $end
$var reg 1 ' rd_n $end
$var reg 1 ( reset $end
$var reg 8 ) wr_data [7:0] $end
$var reg 1 * wr_n $end
$scope module U0 $end
$var wire 3 + addr [2:0] $end
$var wire 1 $ clk $end
$var wire 1 % cs_n $end
$var wire 1 , cts_n $end
$var wire 1 - dcd_n $end
$var wire 1 . dsr_n $end
$var wire 1 & rclk $end
$var wire 1 ' rd_n $end
$var wire 1 ( reset_n $end
$var wire 1 / ri_n $end
$var wire 1 0 sin $end
$var wire 8 1 wr_data [7:0] $end
$var wire 1 * wr_n $end
$var reg 4 2 Bit_Phase [3:0] $end
$var reg 4 3 Brk_Cnt [3:0] $end
$var reg 8 4 DLL [7:0] $end
$var reg 8 5 DLM [7:0] $end
$var reg 8 6 DM0 [7:0] $end
$var reg 8 7 DM1 [7:0] $end
$var reg 8 8 IER [7:0] $end
$var reg 8 9 IIR [7:0] $end
$var reg 8 : LCR [7:0] $end
$var reg 8 ; LSR [7:0] $end
$var reg 8 < MCR [7:0] $end
$var reg 8 = MSR [7:0] $end
$var reg 4 > MSR_In [3:0] $end
$var reg 8 ? RBR [7:0] $end
$var reg 1 @ RXD $end
$var reg 4 A RX_Bit_Cnt [3:0] $end
$var reg 1 B RX_Filtered $end
$var reg 1 C RX_Parity $end
$var reg 8 D RX_ShiftReg [7:0] $end
$var reg 8 E SCR [7:0] $end
$var reg 8 F THR [7:0] $end
$var reg 1 G TXD $end
$var reg 4 H TX_Bit_Cnt [3:0] $end
$var reg 1 I TX_Next_Is_Stop $end
$var reg 1 J TX_Parity $end
$var reg 8 K TX_ShiftReg [7:0] $end
$var reg 1 L TX_Stop_Bit $end
$var reg 1 M TX_Tick $end
$var reg 1 " baudout $end
$var reg 1 N dtr_n $end
$var reg 1 O intr $end
$var reg 1 P out1_n $end
$var reg 1 Q out2_n $end
$var reg 8 R rd_data [7:0] $end
$var reg 1 S rts_n $end
$var reg 1 T sout $end
$scope begin bit_tick $end
$var reg 5 U TX_Cnt [4:0] $end
$upscope $end
$scope begin clk_gen $end
$var reg 16 V Baud_Cnt [15:0] $end
$upscope $end
$scope begin input_filter $end
$var reg 2 W Samples [1:0] $end
$upscope $end
$upscope $end
$upscope $end
$enddefinitions $end
#0
$dumpvars
bx W
bx V
bx U
xT
xS
bx R
xQ
xP
xO
xN
xM
xL
bx K
xJ
xI
bx H
xG
bx F
bx E
bx D
xC
xB
bx A
x@
bx ?
bx >
bx =
bx <
bx ;
bx :
bx 9
bx 8
bx 7
bx 6
bx 5
bx 4
bx 3
bx 2
bx 1
z0
z/
z.
z-
z,
bx +
x*
bx )
0(
x'
1&
0%
0$
bx #
x"
bx !
$end
#5
b0 U
b11 W
b0 V
1$
#6
b0 !
b0 R
b0 7
b0 6
z@
1T
1Q
1P
1S
1N
0M
1B
0"
b0 5
b0 4
b0 E
bx0000 =
b0 <
b0 :
b0 8
b0 F
bz >
0C
b0 A
b0 D
b0 3
b0 2
b0 ?
0L
0I
0J
1G
b0 K
b0 H
b1100000 ;
#7
b0xxx 9
#8
0O
b1 9
#10
0$
1(
#15
b10001 U
b1z W
1$
#16
1"
bz0000 =
#20
0$
b0 )
b0 1
b1 #
b1 +
0*
#25
b10010 U
bz W
1$
#30
0$
b10000000 )
b10000000 1
b11 #
b11 +
#35
b10011 U
1$
#36
b10000000 !
b10000000 R
b10000000 :
#40
b0 !
b0 R
0$
b1 )
b1 1
b0 #
b0 +
#45
b10100 U
1$
#46
b1 !
b1 R
b1 6
b1 4
#50
b0 !
b0 R
0$
b0 )
b0 1
b1 #
b1 +
#55
b10101 U
b1 V
1$
#60
b10000000 !
b10000000 R
0$
b11 )
b11 1
b11 #
b11 +
#65
b10110 U
1$
#66
b11 !
b11 R
b0 6
b11 :
#70
b1100000 !
b1100000 R
0$
b100000 )
b100000 1
b101 #
b101 +
#75
b10111 U
1$
#80
b0 !
b0 R
0$
b1101001 )
b1101001 1
b0 #
b0 +
#85
b11000 U
1$
#86
b1101001 F
b0 ;
#90
0$
#95
b11001 U
1$
#100
0$
#105
b11010 U
1$
#110
0$
#115
b11011 U
1$
#120
0$
#125
b11100 U
1$
#130
0$
#135
b11101 U
1$
#140
0$
#145
b11110 U
1$
#150
0$
#155
b11111 U
1$
#156
1M
#160
0$
#165
b10000 U
1$
#166
0M
b1 H
#170
0$
#175
b10001 U
1$
#180
0$
#185
b10010 U
1$
#190
0$
#195
b10011 U
1$
#200
0$
#205
b10100 U
1$
#210
0$
#215
b10101 U
1$
#220
0$
#225
b10110 U
1$
#230
0$
#235
b10111 U
1$
#240
0$
#245
b11000 U
1$
#250
0$
#255
b11001 U
1$
#260
0$
#265
b11010 U
1$
#270
0$
#275
b11011 U
1$
#280
0$
#285
b11100 U
1$
#290
0$
#295
b11101 U
1$
#300
0$
#305
b11110 U
1$
#310
0$
#315
b11111 U
1$
#316
1M
#320
0$
#325
b10000 U
1$
#326
0T
0M
b10 H
1J
0G
b0 ;
b1101001 K
#330
0$
#335
b10001 U
1$
#340
0$
#345
b10010 U
1$
#350
0$
#355
b10011 U
1$
#360
0$
#365
b10100 U
1$
#370
0$
#375
b10101 U
1$
#380
0$
#385
b10110 U
1$
#390
0$
#395
b10111 U
1$
#400
0$
#405
b11000 U
1$
#410
0$
#415
b11001 U
1$
#420
0$
#425
b11010 U
1$
#430
0$
#435
b11011 U
1$
#440
0$
#445
b11100 U
1$
#450
0$
#455
b11101 U
1$
#460
0$
#465
b11110 U
1$
#470
0$
#475
b11111 U
1$
#476
1M
#480
0$
#485
b10000 U
1$
#486
1T
0M
0J
b110100 K
1G
b11 H
#490
0$
#495
b10001 U
1$
#500
0$
#505
b10010 U
1$
#510
0$
#515
b10011 U
1$
#520
0$
#525
b10100 U
1$
#530
0$
#535
b10101 U
1$
#540
0$
#545
b10110 U
1$
#550
0$
#555
b10111 U
1$
#560
0$
#565
b11000 U
1$
#570
0$
#575
b11001 U
1$
#580
0$
#585
b11010 U
1$
#590
0$
#595
b11011 U
1$
#600
0$
#605
b11100 U
1$
#610
0$
#615
b11101 U
1$
#620
0$
#625
b11110 U
1$
#630
0$
#635
b11111 U
1$
#636
1M
#640
0$
#645
b10000 U
1$
#646
0T
0M
b11010 K
0G
b100 H
#650
0$
#655
b10001 U
1$
#660
0$
#665
b10010 U
1$
#670
0$
#675
b10011 U
1$
#680
0$
#685
b10100 U
1$
#690
0$
#695
b10101 U
1$
#700
0$
#705
b10110 U
1$
#710
0$
#715
b10111 U
1$
#720
0$
#725
b11000 U
1$
#730
0$
#735
b11001 U
1$
#740
0$
#745
b11010 U
1$
#750
0$
#755
b11011 U
1$
#760
0$
#765
b11100 U
1$
#770
0$
#775
b11101 U
1$
#780
0$
#785
b11110 U
1$
#790
0$
#795
b11111 U
1$
#796
1M
#800
0$
#805
b10000 U
1$
#806
0M
b1101 K
b101 H
#810
0$
#815
b10001 U
1$
#820
0$
#825
b10010 U
1$
#830
0$
#835
b10011 U
1$
#840
0$
#845
b10100 U
1$
#850
0$
#855
b10101 U
1$
#860
0$
#865
b10110 U
1$
#870
0$
#875
b10111 U
1$
#880
0$
#885
b11000 U
1$
#890
0$
#895
b11001 U
1$
#900
0$
#905
b11010 U
1$
#910
0$
#915
b11011 U
1$
#920
0$
#925
b11100 U
1$
#930
0$
#935
b11101 U
1$
#940
0$
#945
b11110 U
1$
#950
0$
#955
b11111 U
1$
#956
1M
#960
0$
#965
b10000 U
1$
#966
1T
0M
1J
b110 K
1G
b110 H
#970
0$
#975
b10001 U
1$
#980
0$
#985
b10010 U
1$
#990
0$
#995
b10011 U
1$
#1000
0$
#1005
b10100 U
1$
#1010
0$
#1015
b10101 U
1$
#1020
0$
#1025
b10110 U
1$
#1030
0$
#1035
b10111 U
1$
#1040
0$
#1045
b11000 U
1$
#1050
0$
#1055
b11001 U
1$
#1060
0$
#1065
b11010 U
1$
#1070
0$
#1075
b11011 U
1$
#1080
0$
#1085
b11100 U
1$
#1090
0$
#1095
b11101 U
1$
#1100
0$
#1105
b11110 U
1$
#1110
0$
#1115
b11111 U
1$
#1116
1M
#1120
0$
#1125
b10000 U
1$
#1126
0T
0M
b11 K
0G
b111 H
#1130
0$
#1135
b10001 U
1$
#1140
0$
#1145
b10010 U
1$
#1150
0$
#1155
b10011 U
1$
#1160
0$
#1165
b10100 U
1$
#1170
0$
#1175
b10101 U
1$
#1180
0$
#1185
b10110 U
1$
#1190
0$
#1195
b10111 U
1$
#1200
0$
#1205
b11000 U
1$
#1210
0$
#1215
b11001 U
1$
#1220
0$
#1225
b11010 U
1$
#1230
0$
#1235
b11011 U
1$
#1240
0$
#1245
b11100 U
1$
#1250
0$
#1255
b11101 U
1$
#1260
0$
#1265
b11110 U
1$
#1270
0$
#1275
b11111 U
1$
#1276
1M
#1280
0$
#1285
b10000 U
1$
#1286
1T
0M
0J
b1 K
1G
b1000 H
#1290
0$
#1295
b10001 U
1$
#1300
0$
#1305
b10010 U
1$
#1310
0$
#1315
b10011 U
1$
#1320
0$
#1325
b10100 U
1$
#1330
0$
#1335
b10101 U
1$
#1340
0$
#1345
b10110 U
1$
#1350
0$
#1355
b10111 U
1$
#1360
0$
#1365
b11000 U
1$
#1370
0$
#1375
b11001 U
1$
#1380
0$
#1385
b11010 U
1$
#1390
0$
#1395
b11011 U
1$
#1400
0$
#1405
b11100 U
1$
#1410
0$
#1415
b11101 U
1$
#1420
0$
#1425
b11110 U
1$
#1430
0$
#1435
b11111 U
1$
#1436
1M
#1440
0$
#1445
b10000 U
1$
#1446
0M
1J
b0 K
b1001 H
#1450
0$
#1455
b10001 U
1$
#1460
0$
#1465
b10010 U
1$
#1470
0$
#1475
b10011 U
1$
#1480
0$
#1485
b10100 U
1$
#1490
0$
#1495
b10101 U
1$
#1500
0$
#1505
b10110 U
1$
#1510
0$
#1515
b10111 U
1$
#1520
0$
#1525
b11000 U
1$
#1530
0$
#1535
b11001 U
1$
#1540
0$
#1545
b11010 U
1$
#1550
0$
#1555
b11011 U
1$
#1560
0$
#1565
b11100 U
1$
#1570
0$
#1575
b11101 U
1$
#1580
0$
#1585
b11110 U
1$
#1590
0$
#1595
b11111 U
1$
#1596
1M
#1600
0$
#1605
b10000 U
1$
#1606
0T
0M
0G
b0 ;
1I
b0 H
#1610
0$
#1615
b10001 U
1$
#1620
0$
#1625
b10010 U
1$
#1630
0$
#1635
b10011 U
1$
#1640
0$
#1645
b10100 U
1$
#1650
0$
#1655
b10101 U
1$
#1660
0$
#1665
b10110 U
1$
#1670
0$
#1675
b10111 U
1$
#1680
0$
#1685
b11000 U
1$
#1690
0$
#1695
b11001 U
1$
#1700
0$
#1705
b11010 U
1$
#1710
0$
#1715
b11011 U
1$
#1720
0$
#1725
b11100 U
1$
#1730
0$
#1735
b11101 U
1$
#1740
0$
#1745
b11110 U
1$
#1750
0$
#1755
b11111 U
1$
#1756
1M
#1760
0$
#1765
b10000 U
1$
#1766
1T
0M
1G
b1 H
1L
0I
#1770
0$
#1775
b10001 U
1$
#1780
0$
#1785
b10010 U
1$
#1790
0$
#1795
b10011 U
1$
#1800
0$
#1805
b10100 U
1$
#1810
0$
#1815
b10101 U
1$
#1820
0$
#1825
b10110 U
1$
#1830
0$
#1835
b10111 U
1$
#1840
0$
#1845
b11000 U
1$
#1850
0$
#1855
b11001 U
1$
#1860
0$
#1865
b11010 U
1$
#1870
0$
#1875
b11011 U
1$
#1880
0$
#1885
b11100 U
1$
#1890
0$
#1895
b11101 U
1$
#1900
0$
#1905
b11110 U
1$
#1910
0$
#1915
b11111 U
1$
#1916
1M
#1920
0$
#1925
b10000 U
1$
#1926
0T
0M
b10 H
0G
b0 ;
b1101001 K
0L
#1930
0$
#1935
b10001 U
1$
#1940
0$
#1945
b10010 U
1$
#1950
0$
#1955
b10011 U
1$
#1960
0$
#1965
b10100 U
1$
#1970
0$
#1975
b10101 U
1$
#1980
0$
#1985
b10110 U
1$
#1990
0$
#1995
b10111 U
1$
#2000
0$
#2005
b11000 U
1$
#2010
0$
#2015
b11001 U
1$
#2020
0$
#2025
b11010 U
1$
#2030
0$
#2035
b11011 U
1$
#2040
0$
#2045
b11100 U
1$
#2050
0$
#2055
b11101 U
1$
#2060
0$
#2065
b11110 U
1$
#2070
0$
#2075
b11111 U
1$
#2076
1M
#2080
0$
#2085
b10000 U
1$
#2086
1T
0M
0J
b110100 K
1G
b11 H
#2090
0$
#2095
b10001 U
1$
#2100
0$
#2105
b10010 U
1$
#2110
0$
#2115
b10011 U
1$
#2120
0$
#2125
b10100 U
1$
#2130
0$
#2135
b10101 U
1$
#2140
0$
#2145
b10110 U
1$
#2150
0$
#2155
b10111 U
1$
#2160
0$
#2165
b11000 U
1$
#2170
0$
#2175
b11001 U
1$
#2180
0$
#2185
b11010 U
1$
#2190
0$
#2195
b11011 U
1$
#2200
0$
#2205
b11100 U
1$
#2210
0$
#2215
b11101 U
1$
#2220
0$
#2225
b11110 U
1$
#2230
0$
#2235
b11111 U
1$
#2236
1M
#2240
0$
#2245
b10000 U
1$
#2246
0T
0M
b11010 K
0G
b100 H
#2250
0$
#2255
b10001 U
1$
#2260
0$
#2265
b10010 U
1$
#2270
0$
#2275
b10011 U
1$
#2280
0$
#2285
b10100 U
1$
#2290
0$
#2295
b10101 U
1$
#2300
0$
#2305
b10110 U
1$
#2310
0$
#2315
b10111 U
1$
#2320
0$
#2325
b11000 U
1$
#2330
0$
#2335
b11001 U
1$
#2340
0$
#2345
b11010 U
1$
#2350
0$
#2355
b11011 U
1$
#2360
0$
#2365
b11100 U
1$
#2370
0$
#2375
b11101 U
1$
#2380
0$
#2385
b11110 U
1$
#2390
0$
#2395
b11111 U
1$
#2396
1M
#2400
0$
#2405
b10000 U
1$
#2406
0M
b1101 K
b101 H
#2410
0$
#2415
b10001 U
1$
#2420
0$
#2425
b10010 U
1$
#2430
0$
#2435
b10011 U
1$
#2440
0$
#2445
b10100 U
1$
#2450
0$
#2455
b10101 U
1$
#2460
0$
#2465
b10110 U
1$
