uart.v
//`timescale 1ns / 1ps
// Documented Verilog UART
// Copyright (C) 2010 Timothy Goddard (tim@goddard.net.nz)
// Distributed under the MIT licence.
//
// Permission is hereby granted, free of charge, to any person obtaining a copy
// of this software and associated documentation files (the "Software"), to deal
// in the Software without restriction, including without limitation the rights
// to use, copy, modify, merge, publish, distribute, sublicense, and/or sell
// copies of the Software, and to permit persons to whom the Software is
// furnished to do so, subject to the following conditions:
//
// The above copyright notice and this permission notice shall be included in
// all copies or substantial portions of the Software.
//
// THE SOFTWARE IS PROVIDED "AS IS", WITHOUT WARRANTY OF ANY KIND, EXPRESS OR
// IMPLIED, INCLUDING BUT NOT LIMITED TO THE WARRANTIES OF MERCHANTABILITY,
// FITNESS FOR A PARTICULAR PURPOSE AND NONINFRINGEMENT. IN NO EVENT SHALL THE
// AUTHORS OR COPYRIGHT HOLDERS BE LIABLE FOR ANY CLAIM, DAMAGES OR OTHER
// LIABILITY, WHETHER IN AN ACTION OF CONTRACT, TORT OR OTHERWISE, ARISING FROM,
// OUT OF OR IN CONNECTION WITH THE SOFTWARE OR THE USE OR OTHER DEALINGS IN
// THE SOFTWARE.
//
module uart(
    input clk, // The master clock for this module
    input rst, // Synchronous reset.
    input rx, // Incoming serial line
    output tx, // Outgoing serial line
    input transmit, // Signal to transmit
    input [7:0] tx_byte, // Byte to transmit
    output received, // Indicated that a byte has been received.
    output [7:0] rx_byte, // Byte received
    output is_receiving, // Low when receive line is idle.
    output is_transmitting, // Low when transmit line is idle.
    output recv_error, // Indicates error in receiving packet.
	 output [1:0] state // debugging
    );

parameter CLOCK_DIVIDE = 40;//1302; // clock rate (50Mhz) / (baud rate (9600) * 4)

// States for the receiving state machine.
// These are just constants, not parameters to override.
parameter RX_IDLE = 0;
parameter RX_CHECK_START = 1;
parameter RX_READ_BITS = 2;
parameter RX_CHECK_STOP = 3;
parameter RX_DELAY_RESTART = 4;
parameter RX_ERROR = 5;
parameter RX_RECEIVED = 6;

// States for the transmitting state machine.
// Constants - do not override.
parameter TX_IDLE = 0;
parameter TX_SENDING = 1;
parameter TX_DELAY_RESTART = 2;

reg [10:0] rx_clk_divider = CLOCK_DIVIDE;
reg [10:0] tx_clk_divider = CLOCK_DIVIDE;

reg [2:0] recv_state = RX_IDLE;
reg [5:0] rx_countdown;
reg [3:0] rx_bits_remaining;
reg [7:0] rx_data;

reg tx_out = 1'b1;
reg [1:0] tx_state = TX_IDLE;
reg [5:0] tx_countdown;
reg [3:0] tx_bits_remaining;
reg [7:0] tx_data;

assign received = recv_state == RX_RECEIVED;
assign recv_error = recv_state == RX_ERROR;
assign is_receiving = recv_state != RX_IDLE;
assign rx_byte = rx_data;
assign state = tx_state;

assign tx = tx_out;
assign is_transmitting = tx_state != TX_IDLE;

always @(posedge clk) begin
	if (rst) begin
		recv_state = RX_IDLE;
		tx_state = TX_IDLE;
	end

	// The clk_divider counter counts down from
	// the CLOCK_DIVIDE constant. Whenever it
	// reaches 0, 1/16 of the bit period has elapsed.
   // Countdown timers for the receiving and transmitting
	// state machines are decremented.
	rx_clk_divider = rx_clk_divider - 1;
	if (!rx_clk_divider) begin
		rx_clk_divider = CLOCK_DIVIDE;
		rx_countdown = rx_countdown - 1;
	end
	tx_clk_divider = tx_clk_divider - 1;
	if (!tx_clk_divider) begin
		tx_clk_divider = CLOCK_DIVIDE;
		tx_countdown = tx_countdown - 1;
	end

	// Receive state machine
	case (recv_state)
		RX_IDLE: begin
			// A low pulse on the receive line indicates the
			// start of data.
			if (!rx) begin
				// Wait half the period - should resume in the
				// middle of this first pulse.
				rx_clk_divider = CLOCK_DIVIDE;
				rx_countdown = 2;
				recv_state = RX_CHECK_START;
			end
		end
		RX_CHECK_START: begin
			if (!rx_countdown) begin
				// Check the pulse is still there
				if (!rx) begin
					// Pulse still there - good
					// Wait the bit period to resume half-way
					// through the first bit.
					rx_countdown = 4;
					rx_bits_remaining = 8;
					recv_state = RX_READ_BITS;
				end else begin
					// Pulse lasted less than half the period -
					// not a valid transmission.
					recv_state = RX_ERROR;
				end
			end
		end
		RX_READ_BITS: begin
			if (!rx_countdown) begin
				// Should be half-way through a bit pulse here.
				// Read this bit in, wait for the next if we
				// have more to get.
				rx_data = {rx, rx_data[7:1]};
				rx_countdown = 4;
				rx_bits_remaining = rx_bits_remaining - 1;
				recv_state = rx_bits_remaining ? RX_READ_BITS : RX_CHECK_STOP;
			end
		end
		RX_CHECK_STOP: begin
			if (!rx_countdown) begin
				// Should resume half-way through the stop bit
				// This should be high - if not, reject the
				// transmission and signal an error.
				recv_state = rx ? RX_RECEIVED : RX_ERROR;
			end
		end
		RX_DELAY_RESTART: begin
			// Waits a set number of cycles before accepting
			// another transmission.
			recv_state = rx_countdown ? RX_DELAY_RESTART : RX_IDLE;
		end
		RX_ERROR: begin
			// There was an error receiving.
			// Raises the recv_error flag for one clock
			// cycle while in this state and then waits
			// 2 bit periods before accepting another
			// transmission.
			rx_countdown = 8;
			recv_state = RX_DELAY_RESTART;
		end
		RX_RECEIVED: begin
			// Successfully received a byte.
			// Raises the received flag for one clock
			// cycle while in this state.
			recv_state = RX_IDLE;
		end
	endcase

	// Transmit state machine
	case (tx_state)
		TX_IDLE: begin
			if (transmit) begin
				// If the transmit flag is raised in the idle
				// state, start transmitting the current content
				// of the tx_byte input.
				tx_data = tx_byte;
				// Send the initial, low pulse of 1 bit period
				// to signal the start, followed by the data
				tx_clk_divider = CLOCK_DIVIDE;
				tx_countdown = 4;
				tx_out = 0;
				tx_bits_remaining = 8;
				tx_state = TX_SENDING;
			end
		end
		TX_SENDING: begin
			if (!tx_countdown) begin
				if (tx_bits_remaining) begin
					tx_bits_remaining = tx_bits_remaining - 1;
					tx_out = tx_data[0];
					tx_data = {1'b0, tx_data[7:1]};
					tx_countdown = 4;
					tx_state = TX_SENDING;
				end else begin
					// Set delay to send out 2 stop bits.
					tx_out = 1;
					tx_countdown = 8;
					tx_state = TX_DELAY_RESTART;
				end
			end
		end
		TX_DELAY_RESTART: begin
			// Wait until tx_countdown reaches the end before
			// we send another transmission. This covers the
			// "stop bit" delay.
			tx_state = tx_countdown ? TX_DELAY_RESTART : TX_IDLE;
		end
	endcase
end

endmodule

uart_ctrl.v
// uart controller
// memory mapped by mem_io to 0xffff
//
// initially we will have a single byte 'buffer' on each end

module uart_ctrl(
  clk,
  rst,
  to_send,
  we,
	rx,
	tx
);

input [7:0] to_send;
input we, clk, rst, rx;
output tx;

// internal registers
//reg [7:0] tx_byte, buffer;
reg transmit, tx_toggle;

reg [7:0] tx_byte;
wire [7:0] rx_byte;

uart uart0 (
    .clk (clk),
    .rst (rst),             // Synchronous reset.
    .rx  (rx),              // Incoming serial line
    .tx  (tx),              // Outgoing serial line
    .transmit (transmit),   // Signal to transmit
    .tx_byte  (to_send),    // Byte to transmit
    .received (received),   // Indicated that a byte has been received.
    .rx_byte  (rx_byte),    // Byte received
    .is_receiving (is_receiving), // Low when receive line is idle.
    .is_transmitting  (is_transmitting), // Low when transmit line is idle.
    .recv_error (recv_error)
);

initial begin
  tx_toggle = 0;
end

always @(posedge clk) begin

	if (we && tx_toggle == 0)
	begin
		tx_toggle = 1;
		tx_byte = to_send;
	end
	if (transmit == 1)
		tx_toggle = 0;
end

always @(negedge clk) begin
	if (tx_toggle == 1)
	begin
		transmit = 1;
	end else begin
		transmit = 0;
	end
end

endmodule

uart_tb.v
module uart_tb;
  reg clk, rst;

reg [7:0] tx_byte;
wire [7:0] rx_byte;
wire [1:0] state;
reg trans;

uart_ctrl U0 (
  .clk	(clk),
  .rst	(rst),
  .to_send	(tx_byte),
  .we			(trans)
  );

  initial begin
		clk = 0;
		rst = 0;
		#5
		tx_byte = 69;
		trans = 1;
		#10
		tx_byte = 69;
		trans = 0;
  end

  always
    #5 clk = !clk;

  initial  begin
    $dumpfile("uart.vcd");
    $dumpvars;
  end

  initial  begin
    $display("\t\ttime,\tclk,\ticycle");
    $monitor("%d,\t%b,\t%b",$time, clk,rst);
  end

  initial
  #2000 $finish;

  //Rest of testbench code after this line

endmodule

uart.vcd
$date
	Sat Mar 18 14:09:06 2017
$end
$version
	Icarus Verilog
$end
$timescale
	1s
$end
$scope module uart_tb $end
$var reg 1 ! clk $end
$var reg 1 " rst $end
$var reg 1 # trans $end
$var reg 8 $ tx_byte [7:0] $end
$scope module U0 $end
$var wire 1 ! clk $end
$var wire 1 " rst $end
$var wire 1 % rx $end
$var wire 8 & to_send [7:0] $end
$var wire 1 # we $end
$var wire 1 ' tx $end
$var wire 8 ( rx_byte [7:0] $end
$var wire 1 ) recv_error $end
$var wire 1 * received $end
$var wire 1 + is_transmitting $end
$var wire 1 , is_receiving $end
$var reg 1 - transmit $end
$var reg 8 . tx_byte [7:0] $end
$var reg 1 / tx_toggle $end
$scope module uart0 $end
$var wire 1 ! clk $end
$var wire 1 " rst $end
$var wire 1 % rx $end
$var wire 8 0 rx_byte [7:0] $end
$var wire 2 1 state [1:0] $end
$var wire 1 - transmit $end
$var wire 1 ' tx $end
$var wire 8 2 tx_byte [7:0] $end
$var wire 1 ) recv_error $end
$var wire 1 * received $end
$var wire 1 + is_transmitting $end
$var wire 1 , is_receiving $end
$var reg 3 3 recv_state [2:0] $end
$var reg 4 4 rx_bits_remaining [3:0] $end
$var reg 11 5 rx_clk_divider [10:0] $end
$var reg 6 6 rx_countdown [5:0] $end
$var reg 8 7 rx_data [7:0] $end
$var reg 4 8 tx_bits_remaining [3:0] $end
$var reg 11 9 tx_clk_divider [10:0] $end
$var reg 6 : tx_countdown [5:0] $end
$var reg 8 ; tx_data [7:0] $end
$var reg 1 < tx_out $end
$var reg 2 = tx_state [1:0] $end
$upscope $end
$upscope $end
$upscope $end
$enddefinitions $end
#0
$dumpvars
b0 =
1<
bx ;
bx :
b1 9
bx 8
bx 7
bx 6
b1 5
bx 4
b0 3
bx 2
b0 1
bx 0
0/
bx .
0-
0,
0+
0*
0)
bx (
1'
bx &
z%
bx $
x#
0"
0!
$end
#5
b1 9
b1 5
b1000101 .
1/
1!
1#
b1000101 $
b1000101 &
b1000101 2
#10
0/
1-
0!
#15
1+
b1 1
b1 =
b1000 8
0'
0<
b100 :
b1000101 ;
b1 9
b1 5
1!
0#
#20
0-
0!
#25
b11 :
b1 9
b1 5
1!
#30
0!
#35
b10 :
b1 9
b1 5
1!
#40
0!
#45
b1 :
b1 9
b1 5
1!
#50
0!
#55
b100010 ;
1'
1<
b111 8
b100 :
b1 9
b1 5
1!
#60
0!
#65
b11 :
b1 9
b1 5
1!
#70
0!
#75
b10 :
b1 9
b1 5
1!
#80
0!
#85
b1 :
b1 9
b1 5
1!
#90
0!
#95
b10001 ;
0'
0<
b110 8
b100 :
b1 9
b1 5
1!
#100
0!
#105
b11 :
b1 9
b1 5
1!
#110
0!
#115
b10 :
b1 9
b1 5
1!
#120
0!
#125
b1 :
b1 9
b1 5
1!
#130
0!
#135
b1000 ;
1'
1<
b101 8
b100 :
b1 9
b1 5
1!
#140
0!
#145
b11 :
b1 9
b1 5
1!
#150
0!
#155
b10 :
b1 9
b1 5
1!
#160
0!
#165
b1 :
b1 9
b1 5
1!
#170
0!
#175
b100 ;
0'
0<
b100 8
b100 :
b1 9
b1 5
1!
#180
0!
#185
b11 :
b1 9
b1 5
1!
#190
0!
#195
b10 :
b1 9
b1 5
1!
#200
0!
#205
b1 :
b1 9
b1 5
1!
#210
0!
#215
b10 ;
b11 8
b100 :
b1 9
b1 5
1!
#220
0!
#225
b11 :
b1 9
b1 5
1!
#230
0!
#235
b10 :
b1 9
b1 5
1!
#240
0!
#245
b1 :
b1 9
b1 5
1!
#250
0!
#255
b1 ;
b10 8
b100 :
b1 9
b1 5
1!
#260
0!
#265
b11 :
b1 9
b1 5
1!
#270
0!
#275
b10 :
b1 9
b1 5
1!
#280
0!
#285
b1 :
b1 9
b1 5
1!
#290
0!
#295
b0 ;
1'
1<
b1 8
b100 :
b1 9
b1 5
1!
#300
0!
#305
b11 :
b1 9
b1 5
1!
#310
0!
#315
b10 :
b1 9
b1 5
1!
#320
0!
#325
b1 :
b1 9
b1 5
1!
#330
0!
#335
0'
0<
b0 8
b100 :
b1 9
b1 5
1!
#340
0!
#345
b11 :
b1 9
b1 5
1!
#350
0!
#355
b10 :
b1 9
b1 5
1!
#360
0!
#365
b1 :
b1 9
b1 5
1!
#370
0!
#375
b10 1
b10 =
1'
1<
b1000 :
b1 9
b1 5
1!
#380
0!
#385
b111 :
b1 9
b1 5
1!
#390
0!
#395
b110 :
b1 9
b1 5
1!
#400
0!
#405
b101 :
b1 9
b1 5
1!
#410
0!
#415
b100 :
b1 9
b1 5
1!
#420
0!
#425
b11 :
b1 9
b1 5
1!
#430
0!
#435
b10 :
b1 9
b1 5
1!
#440
0!
#445
b1 :
b1 9
b1 5
1!
#450
0!
#455
0+
b0 1
b0 =
b0 :
b1 9
b1 5
1!
#460
0!
#465
b111111 :
b1 9
b1 5
1!
#470
0!
#475
b111110 :
b1 9
b1 5
1!
#480
0!
#485
b111101 :
b1 9
b1 5
1!
#490
0!
#495
b111100 :
b1 9
b1 5
1!
#500
0!
#505
b111011 :
b1 9
b1 5
1!
#510
0!
#515
b111010 :
b1 9
b1 5
1!
#520
0!
#525
b111001 :
b1 9
b1 5
1!
#530
0!
#535
b111000 :
b1 9
b1 5
1!
#540
0!
#545
b110111 :
b1 9
b1 5
1!
#550
0!
#555
b110110 :
b1 9
b1 5
1!
#560
0!
#565
b110101 :
b1 9
b1 5
1!
#570
0!
#575
b110100 :
b1 9
b1 5
1!
#580
0!
#585
b110011 :
b1 9
b1 5
1!
#590
0!
#595
b110010 :
b1 9
b1 5
1!
#600
0!
#605
b110001 :
b1 9
b1 5
1!
#610
0!
#615
b110000 :
b1 9
b1 5
1!
#620
0!
#625
b101111 :
b1 9
b1 5
1!
#630
0!
#635
b101110 :
b1 9
b1 5
1!
#640
0!
#645
b101101 :
b1 9
b1 5
1!
#650
0!
#655
b101100 :
b1 9
b1 5
1!
#660
0!
#665
b101011 :
b1 9
b1 5
1!
#670
0!
#675
b101010 :
b1 9
b1 5
1!
#680
0!
#685
b101001 :
b1 9
b1 5
1!
#690
0!
#695
b101000 :
b1 9
b1 5
1!
#700
0!
#705
b100111 :
b1 9
b1 5
1!
#710
0!
#715
b100110 :
b1 9
b1 5
1!
#720
0!
#725
b100101 :
b1 9
b1 5
1!
#730
0!
#735
b100100 :
b1 9
b1 5
1!
#740
0!
#745
b100011 :
b1 9
b1 5
1!
#750
0!
#755
b100010 :
b1 9
b1 5
1!
#760
0!
#765
b100001 :
b1 9
b1 5
1!
#770
0!
#775
b100000 :
b1 9
b1 5
1!
#780
0!
#785
b11111 :
b1 9
b1 5
1!
#790
0!
#795
b11110 :
b1 9
b1 5
1!
#800
0!
#805
b11101 :
b1 9
b1 5
1!
#810
0!
#815
b11100 :
b1 9
b1 5
1!
#820
0!
#825
b11011 :
b1 9
b1 5
1!
#830
0!
#835
b11010 :
b1 9
b1 5
1!
#840
0!
#845
b11001 :
b1 9
b1 5
1!
#850
0!
#855
b11000 :
b1 9
b1 5
1!
#860
0!
#865
b10111 :
b1 9
b1 5
1!
#870
0!
#875
b10110 :
b1 9
b1 5
1!
#880
0!
#885
b10101 :
b1 9
b1 5
1!
#890
0!
#895
b10100 :
b1 9
b1 5
1!
#900
0!
#905
b10011 :
b1 9
b1 5
1!
#910
0!
#915
b10010 :
b1 9
b1 5
1!
#920
0!
#925
b10001 :
b1 9
b1 5
1!
#930
0!
#935
b10000 :
b1 9
b1 5
1!
#940
0!
#945
b1111 :
b1 9
b1 5
1!
#950
0!
#955
b1110 :
b1 9
b1 5
1!
#960
0!
#965
b1101 :
b1 9
b1 5
1!
#970
0!
#975
b1100 :
b1 9
b1 5
1!
#980
0!
#985
b1011 :
b1 9
b1 5
1!
#990
0!
#995
b1010 :
b1 9
b1 5
1!
#1000
0!
#1005
b1001 :
b1 9
b1 5
1!
#1010
0!
#1015
b1000 :
b1 9
b1 5
1!
#1020
0!
#1025
b111 :
b1 9
b1 5
1!
#1030
0!
#1035
b110 :
b1 9
b1 5
1!
#1040
0!
#1045
b101 :
b1 9
b1 5
1!
#1050
0!
#1055
b100 :
b1 9
b1 5
1!
#1060
0!
#1065
b11 :
b1 9
b1 5
1!
#1070
0!
#1075
b10 :
b1 9
b1 5
1!
#1080
0!
#1085
b1 :
b1 9
b1 5
1!
#1090
0!
#1095
b0 :
b1 9
b1 5
1!
#1100
0!
#1105
b111111 :
b1 9
b1 5
1!
#1110
0!
#1115
b111110 :
b1 9
b1 5
1!
#1120
0!
#1125
b111101 :
b1 9
b1 5
1!
#1130
0!
#1135
b111100 :
b1 9
b1 5
1!
#1140
0!
#1145
b111011 :
b1 9
b1 5
1!
#1150
0!
#1155
b111010 :
b1 9
b1 5
1!
#1160
0!
#1165
b111001 :
b1 9
b1 5
1!
#1170
0!
#1175
b111000 :
b1 9
b1 5
1!
#1180
0!
#1185
b110111 :
b1 9
b1 5
1!
#1190
0!
#1195
b110110 :
b1 9
b1 5
1!
#1200
0!
#1205
b110101 :
b1 9
b1 5
1!
#1210
0!
#1215
b110100 :
b1 9
b1 5
1!
#1220
0!
#1225
b110011 :
b1 9
b1 5
1!
#1230
0!
#1235
b110010 :
b1 9
b1 5
1!
#1240
0!
#1245
b110001 :
b1 9
b1 5
1!
#1250
0!
#1255
b110000 :
b1 9
b1 5
1!
#1260
0!
#1265
b101111 :
b1 9
b1 5
1!
#1270
0!
#1275
b101110 :
b1 9
b1 5
1!
#1280
0!
#1285
b101101 :
b1 9
b1 5
1!
#1290
0!
#1295
b101100 :
b1 9
b1 5
1!
#1300
0!
#1305
b101011 :
b1 9
b1 5
1!
#1310
0!
#1315
b101010 :
b1 9
b1 5
1!
#1320
0!
#1325
b101001 :
b1 9
b1 5
1!
#1330
0!
#1335
b101000 :
b1 9
b1 5
1!
#1340
0!
#1345
b100111 :
b1 9
b1 5
1!
#1350
0!
#1355
b100110 :
b1 9
b1 5
1!
#1360
0!
#1365
b100101 :
b1 9
b1 5
1!
#1370
0!
#1375
b100100 :
b1 9
b1 5
1!
#1380
0!
#1385
b100011 :
b1 9
b1 5
1!
#1390
0!
#1395
b100010 :
b1 9
b1 5
1!
#1400
0!
#1405
b100001 :
b1 9
b1 5
1!
#1410
0!
#1415
b100000 :
b1 9
b1 5
1!
#1420
0!
#1425
b11111 :
b1 9
b1 5
1!
#1430
0!
#1435
b11110 :
b1 9
b1 5
1!
#1440
0!
#1445
b11101 :
b1 9
b1 5
1!
#1450
0!
#1455
b11100 :
b1 9
b1 5
1!
#1460
0!
#1465
b11011 :
b1 9
b1 5
1!
#1470
0!
#1475
b11010 :
b1 9
b1 5
1!
#1480
0!
#1485
b11001 :
b1 9
b1 5
1!
#1490
0!
#1495
b11000 :
b1 9
b1 5
1!
#1500
0!
#1505
b10111 :
b1 9
b1 5
1!
#1510
0!
#1515
b10110 :
b1 9
b1 5
1!
#1520
0!
#1525
b10101 :
b1 9
b1 5
1!
#1530
0!
#1535
b10100 :
b1 9
b1 5
1!
#1540
0!
#1545
b10011 :
b1 9
b1 5
1!
#1550
0!
#1555
b10010 :
b1 9
b1 5
1!
#1560
0!
#1565
b10001 :
b1 9
b1 5
1!
#1570
0!
#1575
b10000 :
b1 9
b1 5
1!
#1580
0!
#1585
b1111 :
b1 9
b1 5
1!
#1590
0!
#1595
b1110 :
b1 9
b1 5
1!
#1600
0!
#1605
b1101 :
b1 9
b1 5
1!
#1610
0!
#1615
b1100 :
b1 9
b1 5
1!
#1620
0!
#1625
b1011 :
b1 9
b1 5
1!
#1630
0!
#1635
b1010 :
b1 9
b1 5
1!
#1640
0!
#1645
b1001 :
b1 9
b1 5
1!
#1650
0!
#1655
b1000 :
b1 9
b1 5
1!
#1660
0!
#1665
b111 :
b1 9
b1 5
1!
#1670
0!
#1675
b110 :
b1 9
b1 5
1!
#1680
0!
#1685
b101 :
b1 9
b1 5
1!
#1690
0!
#1695
b100 :
b1 9
b1 5
1!
#1700
0!
#1705
b11 :
b1 9
b1 5
1!
#1710
0!
#1715
b10 :
b1 9
b1 5
1!
#1720
0!
#1725
b1 :
b1 9
b1 5
1!
#1730
0!
#1735
b0 :
b1 9
b1 5
1!
#1740
0!
#1745
b111111 :
b1 9
b1 5
1!
#1750
0!
#1755
b111110 :
b1 9
b1 5
1!
#1760
0!
#1765
b111101 :
b1 9
b1 5
1!
#1770
0!
#1775
b111100 :
b1 9
b1 5
1!
#1780
0!
#1785
b111011 :
b1 9
b1 5
1!
#1790
0!
#1795
b111010 :
b1 9
b1 5
1!
#1800
0!
#1805
b111001 :
b1 9
b1 5
1!
#1810
0!
#1815
b111000 :
b1 9
b1 5
1!
#1820
0!
#1825
b110111 :
b1 9
b1 5
1!
#1830
0!
#1835
b110110 :
b1 9
b1 5
1!
#1840
0!
#1845
b110101 :
b1 9
b1 5
1!
#1850
0!
#1855
b110100 :
b1 9
b1 5
1!
#1860
0!
#1865
b110011 :
b1 9
b1 5
1!
#1870
0!
#1875
b110010 :
b1 9
b1 5
1!
#1880
0!
#1885
b110001 :
b1 9
b1 5
1!
#1890
0!
#1895
b110000 :
b1 9
b1 5
1!
#1900
0!
#1905
b101111 :
b1 9
b1 5
1!
#1910
0!
#1915
b101110 :
b1 9
b1 5
1!
#1920
0!
#1925
b101101 :
b1 9
b1 5
1!
#1930
0!
#1935
b101100 :
b1 9
b1 5
1!
#1940
0!
#1945
b101011 :
b1 9
b1 5
1!
#1950
0!
#1955
b101010 :
b1 9
b1 5
1!
#1960
0!
#1965
b101001 :
b1 9
b1 5
1!
#1970
0!
#1975
b101000 :
b1 9
b1 5
1!
#1980
0!
#1985
b100111 :
b1 9
b1 5
1!
#1990
0!
#1995
b100110 :
b1 9
b1 5
1!
